{
"skeleton": { "hash": "aBZrgCCIbbFU8dnHRzFQDW9Sskk", "spine": "3.6.48", "width": 1946, "height": 3452, "images": "./result/" },
"bones": [
	{ "name": "root" },
	{ "name": "area", "parent": "root", "length": 243.39, "rotation": 90 },
	{ "name": "bone", "parent": "root", "length": 254.67, "rotation": 90, "y": 375.37 },
	{ "name": "panel_result", "parent": "area", "length": 221.11, "x": 1005.42, "y": 42.97, "scaleX": 0.8, "scaleY": 0.8 },
	{ "name": "result_back_b", "parent": "root", "length": 233.48, "rotation": 90, "y": 1725.49 },
	{ "name": "result_butten_heart_a", "parent": "root", "length": 79.11, "rotation": 90, "x": -498.48, "y": 778.5 },
	{ "name": "result_butten_heart_b", "parent": "root", "length": 83.27, "rotation": 90, "x": 499.07, "y": 778.5 },
	{ "name": "result_lobby", "parent": "bone", "length": 71.03, "x": 214.25 },
	{ "name": "result_nextstage", "parent": "bone", "length": 89.48, "x": 189.27, "y": -498.26 },
	{ "name": "result_replay", "parent": "bone", "length": 68.7, "rotation": 1.74, "x": 221.98, "y": 496.42 }
],
"slots": [
	{ "name": "result_background", "bone": "root", "attachment": "result_background" },
	{ "name": "result_butten", "bone": "bone", "attachment": "result_butten" },
	{ "name": "result_butten_heart_a", "bone": "result_butten_heart_a", "attachment": "result_butten_heart_a" },
	{ "name": "result_replay", "bone": "result_replay", "attachment": "result_replay" },
	{ "name": "result_lobby", "bone": "result_lobby", "attachment": "result_lobby" },
	{ "name": "result_nextstage_x", "bone": "result_nextstage" },
	{ "name": "result_nextstage", "bone": "result_nextstage", "attachment": "result_nextstage" },
	{ "name": "result_butten_heart_b", "bone": "result_butten_heart_b", "attachment": "result_butten_heart_b" },
	{ "name": "area", "bone": "area", "attachment": "area" },
	{ "name": "result_replay_area", "bone": "result_replay", "attachment": "result_replay_area" },
	{ "name": "result_lobby_area", "bone": "result_lobby", "attachment": "result_lobby_area" },
	{ "name": "result_nextstage_area", "bone": "result_nextstage", "attachment": "result_nextstage_area" },
	{ "name": "result_back_b", "bone": "result_back_b", "attachment": "result_back_b" },
	{ "name": "panel_result", "bone": "panel_result", "attachment": "panel_result" }
],
"skins": {
	"default": {
		"area": {
			"area": {
				"type": "boundingbox",
				"vertexCount": 4,
				"vertices": [ 973.32, 841.32, 973.32, -794.63, 2930.79, -790.09, 2930.79, 827.68 ]
			}
		},
		"panel_result": {
			"panel_result": {
				"type": "boundingbox",
				"vertexCount": 4,
				"vertices": [ 2368.27, 989.08, 11.16, 992.42, 9.11, -1034.97, 2365.86, -1037.94 ]
			}
		},
		"result_back_b": {
			"result_back_b": { "rotation": -90, "width": 500, "height": 887 }
		},
		"result_background": {
			"result_background": { "x": -32.29, "y": 1725.5, "scaleX": 2, "scaleY": 2, "width": 973, "height": 1726 }
		},
		"result_butten": {
			"result_butten": { "x": 186.63, "y": 4.29, "rotation": -90, "width": 1364, "height": 436 }
		},
		"result_butten_heart_a": {
			"result_butten_heart_a": { "x": 81, "y": -0.19, "rotation": -90, "width": 268, "height": 175 }
		},
		"result_butten_heart_b": {
			"result_butten_heart_b": { "x": 81, "y": 0.36, "rotation": -90, "width": 268, "height": 175 }
		},
		"result_lobby": {
			"result_lobby": { "x": 14.38, "y": -2.71, "rotation": -90, "width": 276, "height": 288 }
		},
		"result_lobby_area": {
			"result_lobby_area": {
				"type": "boundingbox",
				"vertexCount": 4,
				"vertices": [ 195.61, 192.59, 195.61, -190.31, -197.7, -186.15, -195.61, 194.67 ]
			}
		},
		"result_nextstage": {
			"result_nextstage": { "x": 44.85, "y": 2.55, "rotation": -90, "width": 278, "height": 197 },
			"result_nextstage_x": { "x": 44.85, "y": 2.55, "rotation": -90, "width": 278, "height": 197 }
		},
		"result_nextstage_area": {
			"result_nextstage_area": {
				"type": "boundingbox",
				"vertexCount": 4,
				"vertices": [ 216.42, 193.53, 216.42, -178.97, -172.72, -181.05, -170.64, 193.53 ]
			}
		},
		"result_replay": {
			"result_replay": { "x": 8.59, "y": -1.89, "rotation": -91.74, "width": 271, "height": 276 }
		},
		"result_replay_area": {
			"result_replay_area": {
				"type": "boundingbox",
				"vertexCount": 4,
				"vertices": [ 189.03, 192.06, -193.7, 203.66, -205.36, -181.15, 179.45, -192.81 ]
			}
		}
	}
},
"animations": {
	"result_lobby": {
		"slots": {
			"result_back_b": {
				"color": [
					{ "time": 0, "color": "ffffff00" }
				]
			},
			"result_background": {
				"color": [
					{ "time": 0.2667, "color": "ffffffff" },
					{ "time": 0.4333, "color": "ffffff00" }
				]
			}
		},
		"bones": {
			"result_lobby": {
				"scale": [
					{ "time": 0, "x": 1, "y": 1 },
					{ "time": 0.1, "x": 1.2, "y": 1.2 },
					{ "time": 0.1667, "x": 1, "y": 1 }
				]
			},
			"bone": {
				"scale": [
					{ "time": 0.2333, "x": 1, "y": 1 },
					{ "time": 0.4, "x": 1.2, "y": 1.2 },
					{ "time": 0.5, "x": 0, "y": 0 }
				]
			},
			"result_butten_heart_b": {
				"translate": [
					{ "time": 0.2333, "x": 0, "y": 0 },
					{ "time": 0.4, "x": 0, "y": 95.33 }
				],
				"scale": [
					{ "time": 0.2333, "x": 1, "y": 1 },
					{ "time": 0.4, "x": 1.2, "y": 1.2 },
					{ "time": 0.5, "x": 0, "y": 0 }
				]
			},
			"result_butten_heart_a": {
				"translate": [
					{ "time": 0.2333, "x": 0, "y": 0 },
					{ "time": 0.4, "x": 0, "y": 95.33 }
				],
				"scale": [
					{ "time": 0.2333, "x": 1, "y": 1 },
					{ "time": 0.4, "x": 1.2, "y": 1.2 },
					{ "time": 0.5, "x": 0, "y": 0 }
				]
			}
		}
	},
	"result_lose_idle": {
		"slots": {
			"result_back_b": {
				"color": [
					{ "time": 0, "color": "ffffff00" }
				]
			},
			"result_butten_heart_b": {
				"color": [
					{ "time": 0, "color": "ffffff00" }
				]
			},
			"result_nextstage": {
				"attachment": [
					{ "time": 0, "name": "result_nextstage_x" }
				]
			},
			"result_nextstage_area": {
				"color": [
					{ "time": 0, "color": "ffffff00" }
				],
				"attachment": [
					{ "time": 0, "name": null }
				]
			}
		},
		"bones": {
			"bone": {
				"translate": [
					{ "time": 0, "x": 0, "y": 0 }
				]
			},
			"area": {
				"translate": [
					{ "time": 0, "x": 0, "y": -6.96 }
				]
			},
			"result_butten_heart_a": {
				"rotate": [
					{ "time": 0, "angle": 0 },
					{ "time": 0.6667, "angle": -9.29 },
					{ "time": 1.3333, "angle": 11.68 },
					{ "time": 2, "angle": 0 }
				],
				"translate": [
					{ "time": 0, "x": 0, "y": 0, "curve": "stepped" },
					{ "time": 2, "x": 0, "y": 0 }
				],
				"scale": [
					{ "time": 0, "x": 1, "y": 1 },
					{ "time": 1, "x": 1.08, "y": 1.08 },
					{ "time": 2, "x": 1, "y": 1 }
				]
			}
		}
	},
	"result_lose_loading": {
		"slots": {
			"result_back_b": {
				"color": [
					{ "time": 0, "color": "ffffff00" }
				]
			},
			"result_background": {
				"color": [
					{ "time": 0, "color": "ffffff00" },
					{ "time": 0.1667, "color": "ffffffff" }
				]
			},
			"result_butten_heart_b": {
				"color": [
					{ "time": 0, "color": "ffffff00" }
				]
			},
			"result_nextstage": {
				"attachment": [
					{ "time": 0, "name": "result_nextstage_x" }
				]
			},
			"result_nextstage_area": {
				"attachment": [
					{ "time": 0, "name": null }
				]
			}
		},
		"bones": {
			"bone": {
				"scale": [
					{ "time": 0, "x": 0, "y": 0 },
					{ "time": 0.1667, "x": 1.2, "y": 1.2 },
					{ "time": 0.2667, "x": 1, "y": 1 }
				]
			},
			"result_butten_heart_a": {
				"scale": [
					{ "time": 0, "x": 0, "y": 0, "curve": "stepped" },
					{ "time": 0.2667, "x": 0, "y": 0 },
					{ "time": 0.3667, "x": 1.2, "y": 1.2 },
					{ "time": 0.4, "x": 1, "y": 1 }
				]
			}
		}
	},
	"result_next_stage": {
		"slots": {
			"result_back_b": {
				"color": [
					{ "time": 0, "color": "ffffff00", "curve": "stepped" },
					{ "time": 0.2333, "color": "ffffff00" },
					{ "time": 0.5, "color": "ffffffff" }
				]
			}
		},
		"bones": {
			"result_back_b": {
				"scale": [
					{ "time": 0, "x": 0, "y": 0, "curve": "stepped" },
					{ "time": 0.2333, "x": 0, "y": 0 },
					{ "time": 0.5, "x": 5.273, "y": 8.466 }
				]
			},
			"result_nextstage": {
				"scale": [
					{ "time": 0, "x": 1, "y": 1 },
					{ "time": 0.1, "x": 1.2, "y": 1.2 },
					{ "time": 0.1667, "x": 1, "y": 1 }
				]
			}
		}
	},
	"result_replay": {
		"slots": {
			"result_back_b": {
				"color": [
					{ "time": 0, "color": "ffffff00" },
					{ "time": 0.2333, "color": "ffffff00" },
					{ "time": 0.5, "color": "ffffffff" }
				]
			}
		},
		"bones": {
			"result_back_b": {
				"scale": [
					{ "time": 0.2333, "x": 0, "y": 0 },
					{ "time": 0.5, "x": 5.127, "y": 8.202 }
				]
			},
			"result_replay": {
				"scale": [
					{ "time": 0, "x": 1, "y": 1 },
					{ "time": 0.1, "x": 1.2, "y": 1.2 },
					{ "time": 0.1667, "x": 1, "y": 1 }
				]
			}
		}
	},
	"result_win_idle": {
		"slots": {
			"result_back_b": {
				"color": [
					{ "time": 0, "color": "ffffff00" }
				]
			}
		},
		"bones": {
			"bone": {
				"translate": [
					{ "time": 0, "x": 0, "y": 0 }
				]
			},
			"area": {
				"translate": [
					{ "time": 0, "x": 0, "y": -6.96 }
				]
			},
			"result_butten_heart_a": {
				"rotate": [
					{ "time": 0, "angle": 0 },
					{ "time": 0.6667, "angle": -9.29 },
					{ "time": 1.3333, "angle": 11.68 },
					{ "time": 2, "angle": 0 }
				],
				"translate": [
					{ "time": 0, "x": 0, "y": 0, "curve": "stepped" },
					{ "time": 2, "x": 0, "y": 0 }
				],
				"scale": [
					{ "time": 0, "x": 1, "y": 1 },
					{ "time": 1, "x": 1.08, "y": 1.08 },
					{ "time": 2, "x": 1, "y": 1 }
				]
			},
			"result_butten_heart_b": {
				"rotate": [
					{ "time": 0, "angle": 0 },
					{ "time": 0.6667, "angle": -13.15 },
					{ "time": 1.3333, "angle": 11.34 },
					{ "time": 2, "angle": 0 }
				],
				"translate": [
					{ "time": 0, "x": 0, "y": 0, "curve": "stepped" },
					{ "time": 2, "x": 0, "y": 0 }
				],
				"scale": [
					{ "time": 0, "x": 1, "y": 1 },
					{ "time": 1, "x": 1.08, "y": 1.08 },
					{ "time": 2, "x": 1, "y": 1 }
				],
				"shear": [
					{ "time": 0, "x": 0, "y": 0, "curve": "stepped" },
					{ "time": 2, "x": 0, "y": 0 }
				]
			}
		}
	},
	"result_win_loading": {
		"slots": {
			"result_back_b": {
				"color": [
					{ "time": 0, "color": "ffffff00" }
				]
			},
			"result_background": {
				"color": [
					{ "time": 0, "color": "ffffff00" },
					{ "time": 0.1667, "color": "ffffffff" }
				]
			}
		},
		"bones": {
			"bone": {
				"scale": [
					{ "time": 0, "x": 0, "y": 0 },
					{ "time": 0.1667, "x": 1.2, "y": 1.2 },
					{ "time": 0.2667, "x": 1, "y": 1 }
				]
			},
			"result_butten_heart_a": {
				"scale": [
					{ "time": 0, "x": 0, "y": 0, "curve": "stepped" },
					{ "time": 0.2667, "x": 0, "y": 0 },
					{ "time": 0.3667, "x": 1.2, "y": 1.2 },
					{ "time": 0.4, "x": 1, "y": 1 }
				]
			},
			"result_butten_heart_b": {
				"scale": [
					{ "time": 0, "x": 0, "y": 0, "curve": "stepped" },
					{ "time": 0.2667, "x": 0, "y": 0 },
					{ "time": 0.3667, "x": 1.2, "y": 1.2 },
					{ "time": 0.4, "x": 1, "y": 1 }
				]
			}
		}
	}
}
}