{
	"BuildNumber":"1",
	"MapName":"map_49",
	"MissionLastRID":"83999999",
	"MonsterLastRID":"83000489",
	"ToolType":"stagetool_f1",
	"ToolVersion":"2",
	"Waves":
	[
		{
			"Events":
			[
				{
					"Scripts":
					[
						{
							"PosX":"-0.07069",
							"PosY":"0.02069",
							"TargetRID":"81000090",
							"Text":"animate show"
						},
						{
							"PosX":"0.017241",
							"PosY":"0.106897",
							"TargetRID":"81000091",
							"Text":"animate show"
						},
						{
							"PosX":"0.231035",
							"PosY":"-0.272414",
							"TargetRID":"81000092",
							"Text":"animate show"
						},
						{
							"PosX":"0.024138",
							"PosY":"-0.082759",
							"TargetRID":"81000093",
							"Text":"animate show"
						},
						{
							"PosX":"0.089655",
							"PosY":"0.048276",
							"TargetRID":"81000094",
							"Text":"animate show"
						},
						{
							"PosX":"-0.127586",
							"PosY":"0.067241",
							"TargetRID":"81000097",
							"Text":"animate count-idle"
						}
					],
					"TimeSec":"0"
				},
				{
					"Monsters":
					[
						{
							"ID":"I_Slime",
							"PosX":"-0.44",
							"PosY":"-0.433333",
							"RID":"83000000"
						}
					],
					"TimeSec":"6"
				},
				{
					"Monsters":
					[
						{
							"ID":"I_Slime",
							"PosX":"-0.44",
							"PosY":"-0.433333",
							"RID":"83000001"
						}
					],
					"TimeSec":"8"
				},
				{
					"Monsters":
					[
						{
							"ID":"I_Slime",
							"PosX":"-0.44",
							"PosY":"-0.433333",
							"RID":"83000002"
						}
					],
					"TimeSec":"10"
				},
				{
					"Monsters":
					[
						{
							"ID":"I_Slime",
							"PosX":"-0.44",
							"PosY":"-0.433333",
							"RID":"83000003"
						}
					],
					"TimeSec":"12"
				},
				{
					"Monsters":
					[
						{
							"ID":"I_Slime",
							"PosX":"-0.44",
							"PosY":"-0.433333",
							"RID":"83000004"
						}
					],
					"TimeSec":"14"
				},
				{
					"Monsters":
					[
						{
							"ID":"I_Slime",
							"PosX":"-0.44",
							"PosY":"-0.433333",
							"RID":"83000005"
						}
					],
					"TimeSec":"16"
				},
				{
					"Monsters":
					[
						{
							"ID":"I_Slime",
							"PosX":"-0.44",
							"PosY":"-0.433333",
							"RID":"83000006"
						}
					],
					"TimeSec":"18"
				},
				{
					"Monsters":
					[
						{
							"ID":"I_Slime",
							"PosX":"-0.44",
							"PosY":"-0.433333",
							"RID":"83000007"
						}
					],
					"TimeSec":"20"
				},
				{
					"Monsters":
					[
						{
							"ID":"I_Slime",
							"PosX":"-0.44",
							"PosY":"-0.433333",
							"RID":"83000008"
						}
					],
					"TimeSec":"22"
				},
				{
					"Monsters":
					[
						{
							"ID":"I_Slime",
							"PosX":"-0.44",
							"PosY":"-0.433333",
							"RID":"83000009"
						}
					],
					"TimeSec":"24"
				},
				{
					"Monsters":
					[
						{
							"ID":"I_Slime",
							"PosX":"-0.44",
							"PosY":"-0.433333",
							"RID":"83000010"
						}
					],
					"TimeSec":"26"
				},
				{
					"Monsters":
					[
						{
							"ID":"I_Slime",
							"PosX":"-0.44",
							"PosY":"-0.433333",
							"RID":"83000011"
						}
					],
					"TimeSec":"27"
				},
				{
					"Monsters":
					[
						{
							"ID":"I_Slime",
							"PosX":"-0.44",
							"PosY":"-0.433333",
							"RID":"83000012"
						}
					],
					"TimeSec":"28"
				},
				{
					"Monsters":
					[
						{
							"ID":"I_Slime",
							"PosX":"-0.44",
							"PosY":"-0.433333",
							"RID":"83000013"
						}
					],
					"TimeSec":"29"
				},
				{
					"Monsters":
					[
						{
							"ID":"I_Slime",
							"PosX":"-0.44",
							"PosY":"-0.433333",
							"RID":"83000014"
						}
					],
					"TimeSec":"30"
				},
				{
					"Monsters":
					[
						{
							"ID":"I_Slime",
							"PosX":"-0.44",
							"PosY":"-0.433333",
							"RID":"83000015"
						}
					],
					"TimeSec":"31"
				},
				{
					"Monsters":
					[
						{
							"ID":"I_Slime",
							"PosX":"-0.44",
							"PosY":"-0.433333",
							"RID":"83000016"
						}
					],
					"TimeSec":"32"
				},
				{
					"Monsters":
					[
						{
							"ID":"I_Slime",
							"PosX":"-0.44",
							"PosY":"-0.433333",
							"RID":"83000017"
						}
					],
					"TimeSec":"33"
				},
				{
					"Monsters":
					[
						{
							"ID":"I_Slime",
							"PosX":"-0.44",
							"PosY":"-0.433333",
							"RID":"83000018"
						}
					],
					"TimeSec":"34"
				},
				{
					"Monsters":
					[
						{
							"ID":"I_Slime",
							"PosX":"-0.44",
							"PosY":"-0.433333",
							"RID":"83000019"
						}
					],
					"TimeSec":"35"
				},
				{
					"Monsters":
					[
						{
							"ID":"I_Slime",
							"PosX":"-0.44",
							"PosY":"-0.433333",
							"RID":"83000020"
						}
					],
					"TimeSec":"37"
				},
				{
					"Monsters":
					[
						{
							"ID":"I_Slime",
							"PosX":"-0.44",
							"PosY":"-0.433333",
							"RID":"83000021"
						}
					],
					"TimeSec":"39"
				},
				{
					"Monsters":
					[
						{
							"ID":"I_Slime",
							"PosX":"-0.44",
							"PosY":"-0.433333",
							"RID":"83000022"
						}
					],
					"TimeSec":"41"
				},
				{
					"Monsters":
					[
						{
							"ID":"I_Slime",
							"PosX":"-0.44",
							"PosY":"-0.433333",
							"RID":"83000023"
						}
					],
					"TimeSec":"43"
				},
				{
					"Monsters":
					[
						{
							"ID":"I_Slime",
							"PosX":"-0.44",
							"PosY":"-0.433333",
							"RID":"83000024"
						}
					],
					"TimeSec":"45"
				},
				{
					"Monsters":
					[
						{
							"ID":"I_Slime",
							"PosX":"-0.44",
							"PosY":"-0.433333",
							"RID":"83000025"
						}
					],
					"TimeSec":"47"
				},
				{
					"Monsters":
					[
						{
							"ID":"I_Slime",
							"PosX":"-0.44",
							"PosY":"-0.433333",
							"RID":"83000026"
						}
					],
					"TimeSec":"49"
				},
				{
					"Monsters":
					[
						{
							"ID":"I_Slime",
							"PosX":"-0.44",
							"PosY":"-0.433333",
							"RID":"83000027"
						}
					],
					"TimeSec":"51"
				},
				{
					"Monsters":
					[
						{
							"ID":"I_Slime",
							"PosX":"-0.44",
							"PosY":"-0.433333",
							"RID":"83000028"
						}
					],
					"TimeSec":"53"
				},
				{
					"Monsters":
					[
						{
							"ID":"I_Slime",
							"PosX":"-0.44",
							"PosY":"-0.433333",
							"RID":"83000029"
						}
					],
					"TimeSec":"55"
				}
			],
			"Title":"Untitled"
		},
		{
			"Events":
			[
				{
					"Scripts":
					[
						{
							"PosX":"0.056897",
							"PosY":"-0.125862",
							"TargetRID":"81000096",
							"Text":"animate count-idle"
						}
					],
					"TimeSec":"0"
				},
				{
					"Monsters":
					[
						{
							"ID":"I_Slime",
							"PosX":"0.44",
							"PosY":"-0.433333",
							"RID":"83000030"
						}
					],
					"TimeSec":"6"
				},
				{
					"Monsters":
					[
						{
							"ID":"I_Slime",
							"PosX":"0.44",
							"PosY":"-0.433333",
							"RID":"83000031"
						}
					],
					"TimeSec":"7"
				},
				{
					"Monsters":
					[
						{
							"ID":"I_Slime",
							"PosX":"0.44",
							"PosY":"-0.433333",
							"RID":"83000032"
						}
					],
					"TimeSec":"8"
				},
				{
					"Monsters":
					[
						{
							"ID":"I_Slime",
							"PosX":"0.44",
							"PosY":"-0.433333",
							"RID":"83000033"
						}
					],
					"TimeSec":"9"
				},
				{
					"Monsters":
					[
						{
							"ID":"I_Slime",
							"PosX":"0.44",
							"PosY":"-0.433333",
							"RID":"83000034"
						}
					],
					"TimeSec":"10"
				},
				{
					"Monsters":
					[
						{
							"ID":"I_Slime",
							"PosX":"0.44",
							"PosY":"-0.433333",
							"RID":"83000035"
						}
					],
					"TimeSec":"11"
				},
				{
					"Monsters":
					[
						{
							"ID":"I_Slime",
							"PosX":"0.44",
							"PosY":"-0.433333",
							"RID":"83000036"
						}
					],
					"TimeSec":"12"
				},
				{
					"Monsters":
					[
						{
							"ID":"I_Slime",
							"PosX":"0.44",
							"PosY":"-0.433333",
							"RID":"83000037"
						}
					],
					"TimeSec":"13"
				},
				{
					"Monsters":
					[
						{
							"ID":"I_Slime",
							"PosX":"0.44",
							"PosY":"-0.433333",
							"RID":"83000038"
						}
					],
					"TimeSec":"14"
				},
				{
					"Monsters":
					[
						{
							"ID":"I_Slime",
							"PosX":"0.44",
							"PosY":"-0.433333",
							"RID":"83000039"
						}
					],
					"TimeSec":"15"
				},
				{
					"Monsters":
					[
						{
							"ID":"I_Slime",
							"PosX":"0.44",
							"PosY":"-0.433333",
							"RID":"83000040"
						}
					],
					"TimeSec":"18"
				},
				{
					"Monsters":
					[
						{
							"ID":"I_Slime",
							"PosX":"0.44",
							"PosY":"-0.433333",
							"RID":"83000041"
						}
					],
					"TimeSec":"20"
				},
				{
					"Monsters":
					[
						{
							"ID":"I_Slime",
							"PosX":"0.44",
							"PosY":"-0.433333",
							"RID":"83000042"
						}
					],
					"TimeSec":"22"
				},
				{
					"Monsters":
					[
						{
							"ID":"I_Slime",
							"PosX":"0.44",
							"PosY":"-0.433333",
							"RID":"83000043"
						}
					],
					"TimeSec":"24"
				},
				{
					"Monsters":
					[
						{
							"ID":"I_Slime",
							"PosX":"0.44",
							"PosY":"-0.433333",
							"RID":"83000044"
						}
					],
					"TimeSec":"26"
				},
				{
					"Monsters":
					[
						{
							"ID":"I_Slime",
							"PosX":"0.44",
							"PosY":"-0.433333",
							"RID":"83000045"
						}
					],
					"TimeSec":"28"
				},
				{
					"Monsters":
					[
						{
							"ID":"I_Slime",
							"PosX":"0.44",
							"PosY":"-0.433333",
							"RID":"83000046"
						}
					],
					"TimeSec":"30"
				},
				{
					"Monsters":
					[
						{
							"ID":"I_Slime",
							"PosX":"0.44",
							"PosY":"-0.433333",
							"RID":"83000047"
						}
					],
					"TimeSec":"32"
				},
				{
					"Monsters":
					[
						{
							"ID":"I_Slime",
							"PosX":"0.44",
							"PosY":"-0.433333",
							"RID":"83000048"
						}
					],
					"TimeSec":"34"
				},
				{
					"Monsters":
					[
						{
							"ID":"I_Slime",
							"PosX":"0.44",
							"PosY":"-0.433333",
							"RID":"83000049"
						}
					],
					"TimeSec":"36"
				},
				{
					"Monsters":
					[
						{
							"ID":"I_Orc",
							"PosX":"0.44",
							"PosY":"-0.433333",
							"RID":"83000050"
						}
					],
					"TimeSec":"39"
				},
				{
					"Monsters":
					[
						{
							"ID":"I_Orc",
							"PosX":"0.44",
							"PosY":"-0.433333",
							"RID":"83000051"
						}
					],
					"TimeSec":"41"
				},
				{
					"Monsters":
					[
						{
							"ID":"I_Orc",
							"PosX":"0.44",
							"PosY":"-0.433333",
							"RID":"83000052"
						}
					],
					"TimeSec":"43"
				},
				{
					"Monsters":
					[
						{
							"ID":"I_Orc",
							"PosX":"0.44",
							"PosY":"-0.433333",
							"RID":"83000053"
						}
					],
					"TimeSec":"45"
				},
				{
					"Monsters":
					[
						{
							"ID":"I_Orc",
							"PosX":"0.44",
							"PosY":"-0.433333",
							"RID":"83000054"
						}
					],
					"TimeSec":"47"
				},
				{
					"Monsters":
					[
						{
							"ID":"I_Orc",
							"PosX":"0.44",
							"PosY":"-0.433333",
							"RID":"83000055"
						}
					],
					"TimeSec":"49"
				},
				{
					"Monsters":
					[
						{
							"ID":"I_Orc",
							"PosX":"0.44",
							"PosY":"-0.433333",
							"RID":"83000056"
						}
					],
					"TimeSec":"51"
				},
				{
					"Monsters":
					[
						{
							"ID":"I_Orc",
							"PosX":"0.44",
							"PosY":"-0.433333",
							"RID":"83000057"
						}
					],
					"TimeSec":"53"
				},
				{
					"Monsters":
					[
						{
							"ID":"I_Orc",
							"PosX":"0.44",
							"PosY":"-0.433333",
							"RID":"83000058"
						}
					],
					"TimeSec":"55"
				},
				{
					"Monsters":
					[
						{
							"ID":"I_Orc",
							"PosX":"0.44",
							"PosY":"-0.433333",
							"RID":"83000059"
						}
					],
					"TimeSec":"57"
				}
			],
			"Title":"Untitled"
		},
		{
			"Events":
			[
				{
					"Scripts":
					[
						{
							"PosX":"0.055172",
							"PosY":"-0.12931",
							"TargetRID":"81000095",
							"Text":"animate count-idle"
						},
						{
							"PosX":"-0.141379",
							"PosY":"0.046552",
							"TargetRID":"81000099",
							"Text":"animate count-idle"
						}
					],
					"TimeSec":"0"
				},
				{
					"Monsters":
					[
						{
							"ID":"I_Slime",
							"PosX":"0",
							"PosY":"-0.45",
							"RID":"83000060"
						},
						{
							"ID":"I_Orc",
							"PosX":"-0.12",
							"PosY":"0.1",
							"RID":"83000080"
						}
					],
					"TimeSec":"6"
				},
				{
					"Monsters":
					[
						{
							"ID":"I_Slime",
							"PosX":"0",
							"PosY":"-0.45",
							"RID":"83000061"
						}
					],
					"TimeSec":"7"
				},
				{
					"Monsters":
					[
						{
							"ID":"I_Slime",
							"PosX":"0",
							"PosY":"-0.45",
							"RID":"83000062"
						},
						{
							"ID":"I_Orc",
							"PosX":"-0.12",
							"PosY":"0.1",
							"RID":"83000081"
						}
					],
					"TimeSec":"8"
				},
				{
					"Monsters":
					[
						{
							"ID":"I_Slime",
							"PosX":"0",
							"PosY":"-0.45",
							"RID":"83000063"
						}
					],
					"TimeSec":"9"
				},
				{
					"Monsters":
					[
						{
							"ID":"I_Slime",
							"PosX":"0",
							"PosY":"-0.45",
							"RID":"83000064"
						},
						{
							"ID":"I_Orc",
							"PosX":"-0.12",
							"PosY":"0.1",
							"RID":"83000082"
						}
					],
					"TimeSec":"10"
				},
				{
					"Monsters":
					[
						{
							"ID":"I_Slime",
							"PosX":"0",
							"PosY":"-0.45",
							"RID":"83000065"
						}
					],
					"TimeSec":"11"
				},
				{
					"Monsters":
					[
						{
							"ID":"I_Slime",
							"PosX":"0",
							"PosY":"-0.45",
							"RID":"83000066"
						},
						{
							"ID":"I_Orc",
							"PosX":"-0.12",
							"PosY":"0.1",
							"RID":"83000083"
						}
					],
					"TimeSec":"12"
				},
				{
					"Monsters":
					[
						{
							"ID":"I_Slime",
							"PosX":"0",
							"PosY":"-0.45",
							"RID":"83000067"
						}
					],
					"TimeSec":"13"
				},
				{
					"Monsters":
					[
						{
							"ID":"I_Slime",
							"PosX":"0",
							"PosY":"-0.45",
							"RID":"83000068"
						},
						{
							"ID":"I_Orc",
							"PosX":"-0.12",
							"PosY":"0.1",
							"RID":"83000084"
						}
					],
					"TimeSec":"14"
				},
				{
					"Monsters":
					[
						{
							"ID":"I_Slime",
							"PosX":"0",
							"PosY":"-0.45",
							"RID":"83000069"
						}
					],
					"TimeSec":"15"
				},
				{
					"Monsters":
					[
						{
							"ID":"I_Orc",
							"PosX":"-0.12",
							"PosY":"0.1",
							"RID":"83000085"
						}
					],
					"TimeSec":"16"
				},
				{
					"Monsters":
					[
						{
							"ID":"I_Orc",
							"PosX":"-0.12",
							"PosY":"0.1",
							"RID":"83000070"
						},
						{
							"ID":"I_Orc",
							"PosX":"-0.12",
							"PosY":"0.1",
							"RID":"83000086"
						}
					],
					"TimeSec":"18"
				},
				{
					"Monsters":
					[
						{
							"ID":"I_Orc",
							"PosX":"-0.12",
							"PosY":"0.1",
							"RID":"83000071"
						},
						{
							"ID":"I_Orc",
							"PosX":"-0.12",
							"PosY":"0.1",
							"RID":"83000087"
						}
					],
					"TimeSec":"20"
				},
				{
					"Monsters":
					[
						{
							"ID":"I_Orc",
							"PosX":"-0.12",
							"PosY":"0.1",
							"RID":"83000072"
						},
						{
							"ID":"I_Orc",
							"PosX":"-0.12",
							"PosY":"0.1",
							"RID":"83000088"
						}
					],
					"TimeSec":"22"
				},
				{
					"Monsters":
					[
						{
							"ID":"I_Orc",
							"PosX":"-0.12",
							"PosY":"0.1",
							"RID":"83000073"
						},
						{
							"ID":"I_Orc",
							"PosX":"-0.12",
							"PosY":"0.1",
							"RID":"83000089"
						}
					],
					"TimeSec":"24"
				},
				{
					"Monsters":
					[
						{
							"ID":"I_Orc",
							"PosX":"-0.12",
							"PosY":"0.1",
							"RID":"83000074"
						}
					],
					"TimeSec":"26"
				},
				{
					"Monsters":
					[
						{
							"ID":"I_Orc",
							"PosX":"-0.12",
							"PosY":"0.1",
							"RID":"83000075"
						}
					],
					"TimeSec":"28"
				},
				{
					"Monsters":
					[
						{
							"ID":"I_Orc",
							"PosX":"-0.12",
							"PosY":"0.1",
							"RID":"83000076"
						}
					],
					"TimeSec":"30"
				},
				{
					"Monsters":
					[
						{
							"ID":"I_Orc",
							"PosX":"-0.12",
							"PosY":"0.1",
							"RID":"83000077"
						}
					],
					"TimeSec":"32"
				},
				{
					"Monsters":
					[
						{
							"ID":"I_Orc",
							"PosX":"-0.12",
							"PosY":"0.1",
							"RID":"83000078"
						}
					],
					"TimeSec":"34"
				},
				{
					"Monsters":
					[
						{
							"ID":"I_Orc",
							"PosX":"-0.12",
							"PosY":"0.1",
							"RID":"83000079"
						}
					],
					"TimeSec":"36"
				},
				{
					"Monsters":
					[
						{
							"ID":"I_Orc",
							"PosX":"-0.12",
							"PosY":"0.1",
							"RID":"83000090"
						},
						{
							"ID":"I_Orc",
							"PosX":"0",
							"PosY":"-0.45",
							"RID":"83000100"
						}
					],
					"TimeSec":"39"
				},
				{
					"Monsters":
					[
						{
							"ID":"I_Slime",
							"PosX":"-0.12",
							"PosY":"0.1",
							"RID":"83000091"
						},
						{
							"ID":"I_Slime",
							"PosX":"0",
							"PosY":"-0.45",
							"RID":"83000101"
						}
					],
					"TimeSec":"41"
				},
				{
					"Monsters":
					[
						{
							"ID":"I_Orc",
							"PosX":"-0.12",
							"PosY":"0.1",
							"RID":"83000092"
						},
						{
							"ID":"I_Orc",
							"PosX":"0",
							"PosY":"-0.45",
							"RID":"83000102"
						}
					],
					"TimeSec":"43"
				},
				{
					"Monsters":
					[
						{
							"ID":"I_Slime",
							"PosX":"-0.12",
							"PosY":"0.1",
							"RID":"83000093"
						},
						{
							"ID":"I_Slime",
							"PosX":"0",
							"PosY":"-0.45",
							"RID":"83000103"
						}
					],
					"TimeSec":"45"
				},
				{
					"Monsters":
					[
						{
							"ID":"I_Orc",
							"PosX":"-0.12",
							"PosY":"0.1",
							"RID":"83000094"
						},
						{
							"ID":"I_Orc",
							"PosX":"0",
							"PosY":"-0.45",
							"RID":"83000104"
						}
					],
					"TimeSec":"47"
				},
				{
					"Monsters":
					[
						{
							"ID":"I_Slime",
							"PosX":"-0.12",
							"PosY":"0.1",
							"RID":"83000095"
						},
						{
							"ID":"I_Slime",
							"PosX":"0",
							"PosY":"-0.45",
							"RID":"83000105"
						}
					],
					"TimeSec":"49"
				},
				{
					"Monsters":
					[
						{
							"ID":"I_Orc",
							"PosX":"-0.12",
							"PosY":"0.1",
							"RID":"83000096"
						},
						{
							"ID":"I_Orc",
							"PosX":"0",
							"PosY":"-0.45",
							"RID":"83000106"
						}
					],
					"TimeSec":"51"
				},
				{
					"Monsters":
					[
						{
							"ID":"I_Slime",
							"PosX":"-0.12",
							"PosY":"0.1",
							"RID":"83000097"
						},
						{
							"ID":"I_Slime",
							"PosX":"0",
							"PosY":"-0.45",
							"RID":"83000107"
						}
					],
					"TimeSec":"53"
				},
				{
					"Monsters":
					[
						{
							"ID":"I_Orc",
							"PosX":"-0.12",
							"PosY":"0.1",
							"RID":"83000098"
						},
						{
							"ID":"I_Orc",
							"PosX":"0",
							"PosY":"-0.45",
							"RID":"83000108"
						}
					],
					"TimeSec":"55"
				},
				{
					"Monsters":
					[
						{
							"ID":"I_Slime",
							"PosX":"-0.12",
							"PosY":"0.1",
							"RID":"83000099"
						},
						{
							"ID":"I_Slime",
							"PosX":"0",
							"PosY":"-0.45",
							"RID":"83000109"
						}
					],
					"TimeSec":"57"
				}
			],
			"Title":"Untitled"
		},
		{
			"Events":
			[
				{
					"Scripts":
					[
						{
							"PosX":"0.118966",
							"PosY":"-0.15",
							"TargetRID":"81000095",
							"Text":"animate count-idle"
						},
						{
							"PosX":"0.127586",
							"PosY":"0.086207",
							"TargetRID":"81000098",
							"Text":"animate count-idle"
						}
					],
					"TimeSec":"0"
				},
				{
					"Monsters":
					[
						{
							"ID":"I_Orc",
							"PosX":"0",
							"PosY":"-0.45",
							"RID":"83000110"
						},
						{
							"ID":"I_Orc",
							"PosX":"0.12",
							"PosY":"0.1",
							"RID":"83000120"
						}
					],
					"TimeSec":"6"
				},
				{
					"Monsters":
					[
						{
							"ID":"I_Orc",
							"PosX":"0",
							"PosY":"-0.45",
							"RID":"83000111"
						},
						{
							"ID":"I_Orc",
							"PosX":"0.12",
							"PosY":"0.1",
							"RID":"83000121"
						}
					],
					"TimeSec":"8"
				},
				{
					"Monsters":
					[
						{
							"ID":"I_Orc",
							"PosX":"0",
							"PosY":"-0.45",
							"RID":"83000112"
						},
						{
							"ID":"I_Orc",
							"PosX":"0.12",
							"PosY":"0.1",
							"RID":"83000122"
						}
					],
					"TimeSec":"10"
				},
				{
					"Monsters":
					[
						{
							"ID":"I_Orc",
							"PosX":"0",
							"PosY":"-0.45",
							"RID":"83000113"
						},
						{
							"ID":"I_Orc",
							"PosX":"0.12",
							"PosY":"0.1",
							"RID":"83000123"
						}
					],
					"TimeSec":"12"
				},
				{
					"Monsters":
					[
						{
							"ID":"I_Orc",
							"PosX":"0",
							"PosY":"-0.45",
							"RID":"83000114"
						},
						{
							"ID":"I_Orc",
							"PosX":"0.12",
							"PosY":"0.1",
							"RID":"83000124"
						}
					],
					"TimeSec":"14"
				},
				{
					"Monsters":
					[
						{
							"ID":"I_Orc",
							"PosX":"0",
							"PosY":"-0.45",
							"RID":"83000115"
						},
						{
							"ID":"I_Orc",
							"PosX":"0.12",
							"PosY":"0.1",
							"RID":"83000125"
						}
					],
					"TimeSec":"16"
				},
				{
					"Monsters":
					[
						{
							"ID":"I_Orc",
							"PosX":"0",
							"PosY":"-0.45",
							"RID":"83000116"
						},
						{
							"ID":"I_Orc",
							"PosX":"0.12",
							"PosY":"0.1",
							"RID":"83000126"
						}
					],
					"TimeSec":"18"
				},
				{
					"Monsters":
					[
						{
							"ID":"I_Orc",
							"PosX":"0",
							"PosY":"-0.45",
							"RID":"83000117"
						},
						{
							"ID":"I_Orc",
							"PosX":"0.12",
							"PosY":"0.1",
							"RID":"83000127"
						}
					],
					"TimeSec":"20"
				},
				{
					"Monsters":
					[
						{
							"ID":"I_Orc",
							"PosX":"0",
							"PosY":"-0.45",
							"RID":"83000118"
						},
						{
							"ID":"I_Orc",
							"PosX":"0.12",
							"PosY":"0.1",
							"RID":"83000128"
						}
					],
					"TimeSec":"22"
				},
				{
					"Monsters":
					[
						{
							"ID":"I_Orc",
							"PosX":"0",
							"PosY":"-0.45",
							"RID":"83000119"
						},
						{
							"ID":"I_Orc",
							"PosX":"0.12",
							"PosY":"0.1",
							"RID":"83000129"
						}
					],
					"TimeSec":"24"
				},
				{
					"Monsters":
					[
						{
							"ID":"I_Slime",
							"PosX":"0",
							"PosY":"-0.45",
							"RID":"83000130"
						},
						{
							"ID":"I_Slime",
							"PosX":"0.12",
							"PosY":"0.1",
							"RID":"83000140"
						}
					],
					"TimeSec":"27"
				},
				{
					"Monsters":
					[
						{
							"ID":"I_Slime",
							"PosX":"0",
							"PosY":"-0.45",
							"RID":"83000131"
						},
						{
							"ID":"I_Slime",
							"PosX":"0.12",
							"PosY":"0.1",
							"RID":"83000141"
						}
					],
					"TimeSec":"28"
				},
				{
					"Monsters":
					[
						{
							"ID":"I_Slime",
							"PosX":"0",
							"PosY":"-0.45",
							"RID":"83000132"
						},
						{
							"ID":"I_Slime",
							"PosX":"0.12",
							"PosY":"0.1",
							"RID":"83000142"
						}
					],
					"TimeSec":"29"
				},
				{
					"Monsters":
					[
						{
							"ID":"I_Slime",
							"PosX":"0",
							"PosY":"-0.45",
							"RID":"83000133"
						},
						{
							"ID":"I_Slime",
							"PosX":"0.12",
							"PosY":"0.1",
							"RID":"83000143"
						}
					],
					"TimeSec":"30"
				},
				{
					"Monsters":
					[
						{
							"ID":"I_Slime",
							"PosX":"0",
							"PosY":"-0.45",
							"RID":"83000134"
						},
						{
							"ID":"I_Slime",
							"PosX":"0.12",
							"PosY":"0.1",
							"RID":"83000144"
						}
					],
					"TimeSec":"31"
				},
				{
					"Monsters":
					[
						{
							"ID":"I_Slime",
							"PosX":"0",
							"PosY":"-0.45",
							"RID":"83000135"
						},
						{
							"ID":"I_Slime",
							"PosX":"0.12",
							"PosY":"0.1",
							"RID":"83000145"
						}
					],
					"TimeSec":"32"
				},
				{
					"Monsters":
					[
						{
							"ID":"I_Slime",
							"PosX":"0",
							"PosY":"-0.45",
							"RID":"83000136"
						},
						{
							"ID":"I_Slime",
							"PosX":"0.12",
							"PosY":"0.1",
							"RID":"83000146"
						}
					],
					"TimeSec":"33"
				},
				{
					"Monsters":
					[
						{
							"ID":"I_Slime",
							"PosX":"0",
							"PosY":"-0.45",
							"RID":"83000137"
						},
						{
							"ID":"I_Slime",
							"PosX":"0.12",
							"PosY":"0.1",
							"RID":"83000147"
						}
					],
					"TimeSec":"34"
				},
				{
					"Monsters":
					[
						{
							"ID":"I_Slime",
							"PosX":"0",
							"PosY":"-0.45",
							"RID":"83000138"
						},
						{
							"ID":"I_Slime",
							"PosX":"0.12",
							"PosY":"0.1",
							"RID":"83000148"
						}
					],
					"TimeSec":"35"
				},
				{
					"Monsters":
					[
						{
							"ID":"I_Slime",
							"PosX":"0",
							"PosY":"-0.45",
							"RID":"83000139"
						},
						{
							"ID":"I_Slime",
							"PosX":"0.12",
							"PosY":"0.1",
							"RID":"83000149"
						}
					],
					"TimeSec":"36"
				},
				{
					"Monsters":
					[
						{
							"ID":"I_Slime",
							"PosX":"0.12",
							"PosY":"0.1",
							"RID":"83000150"
						},
						{
							"ID":"I_Slime",
							"PosX":"0",
							"PosY":"-0.45",
							"RID":"83000160"
						}
					],
					"TimeSec":"39"
				},
				{
					"Monsters":
					[
						{
							"ID":"I_Slime",
							"PosX":"0.12",
							"PosY":"0.1",
							"RID":"83000151"
						},
						{
							"ID":"I_Slime",
							"PosX":"0",
							"PosY":"-0.45",
							"RID":"83000161"
						}
					],
					"TimeSec":"41"
				},
				{
					"Monsters":
					[
						{
							"ID":"I_Slime",
							"PosX":"0.12",
							"PosY":"0.1",
							"RID":"83000152"
						},
						{
							"ID":"I_Slime",
							"PosX":"0",
							"PosY":"-0.45",
							"RID":"83000162"
						}
					],
					"TimeSec":"43"
				},
				{
					"Monsters":
					[
						{
							"ID":"I_Slime",
							"PosX":"0.12",
							"PosY":"0.1",
							"RID":"83000153"
						},
						{
							"ID":"I_Slime",
							"PosX":"0",
							"PosY":"-0.45",
							"RID":"83000163"
						}
					],
					"TimeSec":"45"
				},
				{
					"Monsters":
					[
						{
							"ID":"I_Slime",
							"PosX":"0.12",
							"PosY":"0.1",
							"RID":"83000154"
						},
						{
							"ID":"I_Slime",
							"PosX":"0",
							"PosY":"-0.45",
							"RID":"83000164"
						}
					],
					"TimeSec":"47"
				},
				{
					"Monsters":
					[
						{
							"ID":"I_Slime",
							"PosX":"0.12",
							"PosY":"0.1",
							"RID":"83000155"
						},
						{
							"ID":"I_Slime",
							"PosX":"0",
							"PosY":"-0.45",
							"RID":"83000165"
						}
					],
					"TimeSec":"49"
				},
				{
					"Monsters":
					[
						{
							"ID":"I_Slime",
							"PosX":"0.12",
							"PosY":"0.1",
							"RID":"83000156"
						},
						{
							"ID":"I_Slime",
							"PosX":"0",
							"PosY":"-0.45",
							"RID":"83000166"
						}
					],
					"TimeSec":"51"
				},
				{
					"Monsters":
					[
						{
							"ID":"I_Slime",
							"PosX":"0.12",
							"PosY":"0.1",
							"RID":"83000157"
						},
						{
							"ID":"I_Slime",
							"PosX":"0",
							"PosY":"-0.45",
							"RID":"83000167"
						}
					],
					"TimeSec":"53"
				},
				{
					"Monsters":
					[
						{
							"ID":"I_Slime",
							"PosX":"0.12",
							"PosY":"0.1",
							"RID":"83000158"
						},
						{
							"ID":"I_Slime",
							"PosX":"0",
							"PosY":"-0.45",
							"RID":"83000168"
						}
					],
					"TimeSec":"55"
				},
				{
					"Monsters":
					[
						{
							"ID":"I_Slime",
							"PosX":"0.12",
							"PosY":"0.1",
							"RID":"83000159"
						},
						{
							"ID":"I_Slime",
							"PosX":"0",
							"PosY":"-0.45",
							"RID":"83000169"
						}
					],
					"TimeSec":"57"
				}
			],
			"Title":"Untitled"
		},
		{
			"Events":
			[
				{
					"Scripts":
					[
						{
							"PosX":"0.063793",
							"PosY":"-0.105172",
							"TargetRID":"81000096",
							"Text":"animate count-idle"
						},
						{
							"PosX":"-0.056897",
							"PosY":"-0.175862",
							"TargetRID":"81000097",
							"Text":"animate count-idle"
						}
					],
					"TimeSec":"0"
				},
				{
					"Monsters":
					[
						{
							"ID":"I_Slime",
							"PosX":"-0.44",
							"PosY":"-0.433333",
							"RID":"83000170"
						},
						{
							"ID":"I_Slime",
							"PosX":"0.44",
							"PosY":"-0.433333",
							"RID":"83000180"
						}
					],
					"TimeSec":"6"
				},
				{
					"Monsters":
					[
						{
							"ID":"I_Slime",
							"PosX":"-0.44",
							"PosY":"-0.433333",
							"RID":"83000171"
						},
						{
							"ID":"I_Slime",
							"PosX":"0.44",
							"PosY":"-0.433333",
							"RID":"83000181"
						}
					],
					"TimeSec":"7"
				},
				{
					"Monsters":
					[
						{
							"ID":"I_Slime",
							"PosX":"-0.44",
							"PosY":"-0.433333",
							"RID":"83000172"
						},
						{
							"ID":"I_Slime",
							"PosX":"0.44",
							"PosY":"-0.433333",
							"RID":"83000182"
						}
					],
					"TimeSec":"8"
				},
				{
					"Monsters":
					[
						{
							"ID":"I_Slime",
							"PosX":"-0.44",
							"PosY":"-0.433333",
							"RID":"83000173"
						},
						{
							"ID":"I_Slime",
							"PosX":"0.44",
							"PosY":"-0.433333",
							"RID":"83000183"
						}
					],
					"TimeSec":"9"
				},
				{
					"Monsters":
					[
						{
							"ID":"I_Slime",
							"PosX":"-0.44",
							"PosY":"-0.433333",
							"RID":"83000174"
						},
						{
							"ID":"I_Slime",
							"PosX":"0.44",
							"PosY":"-0.433333",
							"RID":"83000184"
						}
					],
					"TimeSec":"10"
				},
				{
					"Monsters":
					[
						{
							"ID":"I_Slime",
							"PosX":"-0.44",
							"PosY":"-0.433333",
							"RID":"83000175"
						},
						{
							"ID":"I_Slime",
							"PosX":"0.44",
							"PosY":"-0.433333",
							"RID":"83000185"
						}
					],
					"TimeSec":"11"
				},
				{
					"Monsters":
					[
						{
							"ID":"I_Slime",
							"PosX":"-0.44",
							"PosY":"-0.433333",
							"RID":"83000176"
						},
						{
							"ID":"I_Slime",
							"PosX":"0.44",
							"PosY":"-0.433333",
							"RID":"83000186"
						}
					],
					"TimeSec":"12"
				},
				{
					"Monsters":
					[
						{
							"ID":"I_Slime",
							"PosX":"-0.44",
							"PosY":"-0.433333",
							"RID":"83000177"
						},
						{
							"ID":"I_Slime",
							"PosX":"0.44",
							"PosY":"-0.433333",
							"RID":"83000187"
						}
					],
					"TimeSec":"13"
				},
				{
					"Monsters":
					[
						{
							"ID":"I_Slime",
							"PosX":"-0.44",
							"PosY":"-0.433333",
							"RID":"83000178"
						},
						{
							"ID":"I_Slime",
							"PosX":"0.44",
							"PosY":"-0.433333",
							"RID":"83000188"
						}
					],
					"TimeSec":"14"
				},
				{
					"Monsters":
					[
						{
							"ID":"I_Slime",
							"PosX":"-0.44",
							"PosY":"-0.433333",
							"RID":"83000179"
						},
						{
							"ID":"I_Slime",
							"PosX":"0.44",
							"PosY":"-0.433333",
							"RID":"83000189"
						}
					],
					"TimeSec":"15"
				},
				{
					"Monsters":
					[
						{
							"ID":"I_Slime",
							"PosX":"-0.44",
							"PosY":"-0.433333",
							"RID":"83000190"
						},
						{
							"ID":"I_Slime",
							"PosX":"0.44",
							"PosY":"-0.433333",
							"RID":"83000200"
						}
					],
					"TimeSec":"19"
				},
				{
					"Monsters":
					[
						{
							"ID":"I_Slime",
							"PosX":"-0.44",
							"PosY":"-0.433333",
							"RID":"83000191"
						},
						{
							"ID":"I_Slime",
							"PosX":"0.44",
							"PosY":"-0.433333",
							"RID":"83000201"
						}
					],
					"TimeSec":"20"
				},
				{
					"Monsters":
					[
						{
							"ID":"I_Slime",
							"PosX":"-0.44",
							"PosY":"-0.433333",
							"RID":"83000192"
						},
						{
							"ID":"I_Slime",
							"PosX":"0.44",
							"PosY":"-0.433333",
							"RID":"83000202"
						}
					],
					"TimeSec":"21"
				},
				{
					"Monsters":
					[
						{
							"ID":"I_Slime",
							"PosX":"-0.44",
							"PosY":"-0.433333",
							"RID":"83000193"
						},
						{
							"ID":"I_Slime",
							"PosX":"0.44",
							"PosY":"-0.433333",
							"RID":"83000203"
						}
					],
					"TimeSec":"22"
				},
				{
					"Monsters":
					[
						{
							"ID":"I_Slime",
							"PosX":"-0.44",
							"PosY":"-0.433333",
							"RID":"83000194"
						},
						{
							"ID":"I_Slime",
							"PosX":"0.44",
							"PosY":"-0.433333",
							"RID":"83000204"
						}
					],
					"TimeSec":"23"
				},
				{
					"Monsters":
					[
						{
							"ID":"I_Slime",
							"PosX":"-0.44",
							"PosY":"-0.433333",
							"RID":"83000195"
						},
						{
							"ID":"I_Slime",
							"PosX":"0.44",
							"PosY":"-0.433333",
							"RID":"83000205"
						}
					],
					"TimeSec":"24"
				},
				{
					"Monsters":
					[
						{
							"ID":"I_Slime",
							"PosX":"-0.44",
							"PosY":"-0.433333",
							"RID":"83000196"
						},
						{
							"ID":"I_Slime",
							"PosX":"0.44",
							"PosY":"-0.433333",
							"RID":"83000206"
						}
					],
					"TimeSec":"25"
				},
				{
					"Monsters":
					[
						{
							"ID":"I_Slime",
							"PosX":"-0.44",
							"PosY":"-0.433333",
							"RID":"83000197"
						},
						{
							"ID":"I_Slime",
							"PosX":"0.44",
							"PosY":"-0.433333",
							"RID":"83000207"
						}
					],
					"TimeSec":"26"
				},
				{
					"Monsters":
					[
						{
							"ID":"I_Slime",
							"PosX":"-0.44",
							"PosY":"-0.433333",
							"RID":"83000198"
						},
						{
							"ID":"I_Slime",
							"PosX":"0.44",
							"PosY":"-0.433333",
							"RID":"83000208"
						}
					],
					"TimeSec":"27"
				},
				{
					"Monsters":
					[
						{
							"ID":"I_Slime",
							"PosX":"-0.44",
							"PosY":"-0.433333",
							"RID":"83000199"
						},
						{
							"ID":"I_Slime",
							"PosX":"0.44",
							"PosY":"-0.433333",
							"RID":"83000209"
						}
					],
					"TimeSec":"28"
				},
				{
					"Monsters":
					[
						{
							"ID":"I_Orc",
							"PosX":"-0.44",
							"PosY":"-0.433333",
							"RID":"83000210"
						},
						{
							"ID":"I_Orc",
							"PosX":"0.44",
							"PosY":"-0.433333",
							"RID":"83000220"
						}
					],
					"TimeSec":"31"
				},
				{
					"Monsters":
					[
						{
							"ID":"I_Orc",
							"PosX":"-0.44",
							"PosY":"-0.433333",
							"RID":"83000211"
						},
						{
							"ID":"I_Orc",
							"PosX":"0.44",
							"PosY":"-0.433333",
							"RID":"83000221"
						}
					],
					"TimeSec":"32"
				},
				{
					"Monsters":
					[
						{
							"ID":"I_Orc",
							"PosX":"-0.44",
							"PosY":"-0.433333",
							"RID":"83000212"
						},
						{
							"ID":"I_Orc",
							"PosX":"0.44",
							"PosY":"-0.433333",
							"RID":"83000222"
						}
					],
					"TimeSec":"33"
				},
				{
					"Monsters":
					[
						{
							"ID":"I_Orc",
							"PosX":"-0.44",
							"PosY":"-0.433333",
							"RID":"83000213"
						},
						{
							"ID":"I_Orc",
							"PosX":"0.44",
							"PosY":"-0.433333",
							"RID":"83000223"
						}
					],
					"TimeSec":"34"
				},
				{
					"Monsters":
					[
						{
							"ID":"I_Orc",
							"PosX":"-0.44",
							"PosY":"-0.433333",
							"RID":"83000214"
						},
						{
							"ID":"I_Orc",
							"PosX":"0.44",
							"PosY":"-0.433333",
							"RID":"83000224"
						}
					],
					"TimeSec":"35"
				},
				{
					"Monsters":
					[
						{
							"ID":"I_Orc",
							"PosX":"-0.44",
							"PosY":"-0.433333",
							"RID":"83000215"
						},
						{
							"ID":"I_Orc",
							"PosX":"0.44",
							"PosY":"-0.433333",
							"RID":"83000225"
						}
					],
					"TimeSec":"36"
				},
				{
					"Monsters":
					[
						{
							"ID":"I_Orc",
							"PosX":"-0.44",
							"PosY":"-0.433333",
							"RID":"83000216"
						},
						{
							"ID":"I_Orc",
							"PosX":"0.44",
							"PosY":"-0.433333",
							"RID":"83000226"
						}
					],
					"TimeSec":"37"
				},
				{
					"Monsters":
					[
						{
							"ID":"I_Orc",
							"PosX":"-0.44",
							"PosY":"-0.433333",
							"RID":"83000217"
						},
						{
							"ID":"I_Orc",
							"PosX":"0.44",
							"PosY":"-0.433333",
							"RID":"83000227"
						}
					],
					"TimeSec":"38"
				},
				{
					"Monsters":
					[
						{
							"ID":"I_Orc",
							"PosX":"-0.44",
							"PosY":"-0.433333",
							"RID":"83000218"
						},
						{
							"ID":"I_Orc",
							"PosX":"0.44",
							"PosY":"-0.433333",
							"RID":"83000228"
						}
					],
					"TimeSec":"39"
				},
				{
					"Monsters":
					[
						{
							"ID":"I_Orc",
							"PosX":"-0.44",
							"PosY":"-0.433333",
							"RID":"83000219"
						},
						{
							"ID":"I_Orc",
							"PosX":"0.44",
							"PosY":"-0.433333",
							"RID":"83000229"
						}
					],
					"TimeSec":"40"
				}
			],
			"Title":"Untitled"
		},
		{
			"Events":
			[
				{
					"Scripts":
					[
						{
							"PosX":"0.191379",
							"PosY":"0.077586",
							"TargetRID":"81000098",
							"Text":"animate count-idle"
						},
						{
							"PosX":"-0.137931",
							"PosY":"0.07069",
							"TargetRID":"81000099",
							"Text":"animate count-idle"
						}
					],
					"TimeSec":"0"
				},
				{
					"Monsters":
					[
						{
							"ID":"I_Orc",
							"PosX":"-0.12",
							"PosY":"0.1",
							"RID":"83000230"
						},
						{
							"ID":"I_Orc",
							"PosX":"0.12",
							"PosY":"0.1",
							"RID":"83000240"
						}
					],
					"TimeSec":"6"
				},
				{
					"Monsters":
					[
						{
							"ID":"I_Slime",
							"PosX":"-0.12",
							"PosY":"0.1",
							"RID":"83000231"
						},
						{
							"ID":"I_Slime",
							"PosX":"0.12",
							"PosY":"0.1",
							"RID":"83000241"
						}
					],
					"TimeSec":"8"
				},
				{
					"Monsters":
					[
						{
							"ID":"I_Orc",
							"PosX":"-0.12",
							"PosY":"0.1",
							"RID":"83000232"
						},
						{
							"ID":"I_Orc",
							"PosX":"0.12",
							"PosY":"0.1",
							"RID":"83000242"
						}
					],
					"TimeSec":"10"
				},
				{
					"Monsters":
					[
						{
							"ID":"I_Slime",
							"PosX":"-0.12",
							"PosY":"0.1",
							"RID":"83000233"
						},
						{
							"ID":"I_Slime",
							"PosX":"0.12",
							"PosY":"0.1",
							"RID":"83000243"
						}
					],
					"TimeSec":"12"
				},
				{
					"Monsters":
					[
						{
							"ID":"I_Orc",
							"PosX":"-0.12",
							"PosY":"0.1",
							"RID":"83000234"
						},
						{
							"ID":"I_Orc",
							"PosX":"0.12",
							"PosY":"0.1",
							"RID":"83000244"
						}
					],
					"TimeSec":"14"
				},
				{
					"Monsters":
					[
						{
							"ID":"I_Slime",
							"PosX":"-0.12",
							"PosY":"0.1",
							"RID":"83000235"
						},
						{
							"ID":"I_Slime",
							"PosX":"0.12",
							"PosY":"0.1",
							"RID":"83000245"
						}
					],
					"TimeSec":"16"
				},
				{
					"Monsters":
					[
						{
							"ID":"I_Orc",
							"PosX":"-0.12",
							"PosY":"0.1",
							"RID":"83000236"
						},
						{
							"ID":"I_Orc",
							"PosX":"0.12",
							"PosY":"0.1",
							"RID":"83000246"
						}
					],
					"TimeSec":"18"
				},
				{
					"Monsters":
					[
						{
							"ID":"I_Slime",
							"PosX":"-0.12",
							"PosY":"0.1",
							"RID":"83000237"
						},
						{
							"ID":"I_Slime",
							"PosX":"0.12",
							"PosY":"0.1",
							"RID":"83000247"
						}
					],
					"TimeSec":"20"
				},
				{
					"Monsters":
					[
						{
							"ID":"I_Orc",
							"PosX":"-0.12",
							"PosY":"0.1",
							"RID":"83000238"
						},
						{
							"ID":"I_Orc",
							"PosX":"0.12",
							"PosY":"0.1",
							"RID":"83000248"
						}
					],
					"TimeSec":"22"
				},
				{
					"Monsters":
					[
						{
							"ID":"I_Slime",
							"PosX":"-0.12",
							"PosY":"0.1",
							"RID":"83000239"
						},
						{
							"ID":"I_Slime",
							"PosX":"0.12",
							"PosY":"0.1",
							"RID":"83000249"
						}
					],
					"TimeSec":"24"
				},
				{
					"Monsters":
					[
						{
							"ID":"I_Orc",
							"PosX":"-0.12",
							"PosY":"0.1",
							"RID":"83000250"
						},
						{
							"ID":"I_Orc",
							"PosX":"0.12",
							"PosY":"0.1",
							"RID":"83000260"
						}
					],
					"TimeSec":"29"
				},
				{
					"Monsters":
					[
						{
							"ID":"I_Slime",
							"PosX":"-0.12",
							"PosY":"0.1",
							"RID":"83000251"
						},
						{
							"ID":"I_Slime",
							"PosX":"0.12",
							"PosY":"0.1",
							"RID":"83000261"
						}
					],
					"TimeSec":"31"
				},
				{
					"Monsters":
					[
						{
							"ID":"I_Orc",
							"PosX":"-0.12",
							"PosY":"0.1",
							"RID":"83000252"
						},
						{
							"ID":"I_Orc",
							"PosX":"0.12",
							"PosY":"0.1",
							"RID":"83000262"
						}
					],
					"TimeSec":"33"
				},
				{
					"Monsters":
					[
						{
							"ID":"I_Slime",
							"PosX":"-0.12",
							"PosY":"0.1",
							"RID":"83000253"
						},
						{
							"ID":"I_Slime",
							"PosX":"0.12",
							"PosY":"0.1",
							"RID":"83000263"
						}
					],
					"TimeSec":"35"
				},
				{
					"Monsters":
					[
						{
							"ID":"I_Orc",
							"PosX":"-0.12",
							"PosY":"0.1",
							"RID":"83000254"
						},
						{
							"ID":"I_Orc",
							"PosX":"0.12",
							"PosY":"0.1",
							"RID":"83000264"
						}
					],
					"TimeSec":"37"
				},
				{
					"Monsters":
					[
						{
							"ID":"I_Slime",
							"PosX":"-0.12",
							"PosY":"0.1",
							"RID":"83000255"
						},
						{
							"ID":"I_Slime",
							"PosX":"0.12",
							"PosY":"0.1",
							"RID":"83000265"
						}
					],
					"TimeSec":"39"
				},
				{
					"Monsters":
					[
						{
							"ID":"I_Orc",
							"PosX":"-0.12",
							"PosY":"0.1",
							"RID":"83000256"
						},
						{
							"ID":"I_Orc",
							"PosX":"0.12",
							"PosY":"0.1",
							"RID":"83000266"
						}
					],
					"TimeSec":"41"
				},
				{
					"Monsters":
					[
						{
							"ID":"I_Slime",
							"PosX":"-0.12",
							"PosY":"0.1",
							"RID":"83000257"
						},
						{
							"ID":"I_Slime",
							"PosX":"0.12",
							"PosY":"0.1",
							"RID":"83000267"
						}
					],
					"TimeSec":"43"
				},
				{
					"Monsters":
					[
						{
							"ID":"I_Orc",
							"PosX":"-0.12",
							"PosY":"0.1",
							"RID":"83000258"
						},
						{
							"ID":"I_Orc",
							"PosX":"0.12",
							"PosY":"0.1",
							"RID":"83000268"
						}
					],
					"TimeSec":"45"
				},
				{
					"Monsters":
					[
						{
							"ID":"I_Slime",
							"PosX":"-0.12",
							"PosY":"0.1",
							"RID":"83000259"
						},
						{
							"ID":"I_Slime",
							"PosX":"0.12",
							"PosY":"0.1",
							"RID":"83000269"
						}
					],
					"TimeSec":"47"
				}
			],
			"Title":"Untitled"
		},
		{
			"Events":
			[
				{
					"Scripts":
					[
						{
							"PosX":"-0.031034",
							"PosY":"0.091379",
							"TargetRID":"81000090",
							"Text":"animate hiding-idle"
						},
						{
							"PosX":"0.136207",
							"PosY":"-0.218966",
							"TargetRID":"81000091",
							"Text":"animate hiding-idle"
						},
						{
							"PosX":"0.251724",
							"PosY":"0.118966",
							"TargetRID":"81000092",
							"Text":"animate hiding-idle"
						},
						{
							"PosX":"0.274138",
							"PosY":"0.113793",
							"TargetRID":"81000093",
							"Text":"animate hiding-idle"
						},
						{
							"PosX":"0.289655",
							"PosY":"-0.127586",
							"TargetRID":"81000094",
							"Text":"animate hiding-idle"
						},
						{
							"PosX":"0.081034",
							"PosY":"-0.136207",
							"TargetRID":"81000095",
							"Text":"animate count-idle"
						}
					],
					"TimeSec":"0"
				},
				{
					"Monsters":
					[
						{
							"ID":"I_Orc",
							"PosX":"0",
							"PosY":"-0.45",
							"RID":"83000270"
						}
					],
					"TimeSec":"6"
				},
				{
					"Monsters":
					[
						{
							"ID":"I_Slime",
							"PosX":"0",
							"PosY":"-0.45",
							"RID":"83000271"
						}
					],
					"TimeSec":"8"
				},
				{
					"Monsters":
					[
						{
							"ID":"I_Orc",
							"PosX":"0",
							"PosY":"-0.45",
							"RID":"83000272"
						}
					],
					"TimeSec":"10"
				},
				{
					"Monsters":
					[
						{
							"ID":"I_Slime",
							"PosX":"0",
							"PosY":"-0.45",
							"RID":"83000273"
						}
					],
					"TimeSec":"12"
				},
				{
					"Monsters":
					[
						{
							"ID":"I_Orc",
							"PosX":"0",
							"PosY":"-0.45",
							"RID":"83000274"
						}
					],
					"TimeSec":"14"
				},
				{
					"Monsters":
					[
						{
							"ID":"I_Slime",
							"PosX":"0",
							"PosY":"-0.45",
							"RID":"83000275"
						}
					],
					"TimeSec":"16"
				},
				{
					"Monsters":
					[
						{
							"ID":"I_Orc",
							"PosX":"0",
							"PosY":"-0.45",
							"RID":"83000276"
						}
					],
					"TimeSec":"18"
				},
				{
					"Monsters":
					[
						{
							"ID":"I_Slime",
							"PosX":"0",
							"PosY":"-0.45",
							"RID":"83000277"
						}
					],
					"TimeSec":"20"
				},
				{
					"Monsters":
					[
						{
							"ID":"I_Orc",
							"PosX":"0",
							"PosY":"-0.45",
							"RID":"83000278"
						}
					],
					"TimeSec":"22"
				},
				{
					"Monsters":
					[
						{
							"ID":"I_Slime",
							"PosX":"0",
							"PosY":"-0.45",
							"RID":"83000279"
						}
					],
					"TimeSec":"24"
				},
				{
					"Monsters":
					[
						{
							"ID":"I_Orc",
							"PosX":"0",
							"PosY":"-0.45",
							"RID":"83000280"
						}
					],
					"TimeSec":"27"
				},
				{
					"Monsters":
					[
						{
							"ID":"I_Slime",
							"PosX":"0",
							"PosY":"-0.45",
							"RID":"83000281"
						}
					],
					"TimeSec":"29"
				},
				{
					"Monsters":
					[
						{
							"ID":"I_Orc",
							"PosX":"0",
							"PosY":"-0.45",
							"RID":"83000282"
						}
					],
					"TimeSec":"31"
				},
				{
					"Monsters":
					[
						{
							"ID":"I_Slime",
							"PosX":"0",
							"PosY":"-0.45",
							"RID":"83000283"
						}
					],
					"TimeSec":"33"
				},
				{
					"Monsters":
					[
						{
							"ID":"I_Orc",
							"PosX":"0",
							"PosY":"-0.45",
							"RID":"83000284"
						}
					],
					"TimeSec":"35"
				},
				{
					"Monsters":
					[
						{
							"ID":"I_Slime",
							"PosX":"0",
							"PosY":"-0.45",
							"RID":"83000285"
						}
					],
					"TimeSec":"37"
				},
				{
					"Monsters":
					[
						{
							"ID":"I_Orc",
							"PosX":"0",
							"PosY":"-0.45",
							"RID":"83000286"
						}
					],
					"TimeSec":"39"
				},
				{
					"Monsters":
					[
						{
							"ID":"I_Slime",
							"PosX":"0",
							"PosY":"-0.45",
							"RID":"83000287"
						}
					],
					"TimeSec":"41"
				},
				{
					"Monsters":
					[
						{
							"ID":"I_Orc",
							"PosX":"0",
							"PosY":"-0.45",
							"RID":"83000288"
						}
					],
					"TimeSec":"43"
				},
				{
					"Monsters":
					[
						{
							"ID":"I_Slime",
							"PosX":"0",
							"PosY":"-0.45",
							"RID":"83000289"
						}
					],
					"TimeSec":"45"
				}
			],
			"Title":"Untitled"
		},
		{
			"Events":
			[
				{
					"Scripts":
					[
						{
							"PosX":"0.15",
							"PosY":"0.037931",
							"TargetRID":"81000098",
							"Text":"animate count-idle"
						},
						{
							"PosX":"-0.113793",
							"PosY":"0.072414",
							"TargetRID":"81000099",
							"Text":"animate count-idle"
						}
					],
					"TimeSec":"0"
				},
				{
					"Monsters":
					[
						{
							"ID":"I_Orc",
							"PosX":"-0.12",
							"PosY":"0.1",
							"RID":"83000290"
						},
						{
							"ID":"I_Orc",
							"PosX":"0.12",
							"PosY":"0.1",
							"RID":"83000300"
						}
					],
					"TimeSec":"6"
				},
				{
					"Monsters":
					[
						{
							"ID":"I_Orc",
							"PosX":"-0.12",
							"PosY":"0.1",
							"RID":"83000291"
						},
						{
							"ID":"I_Orc",
							"PosX":"0.12",
							"PosY":"0.1",
							"RID":"83000301"
						}
					],
					"TimeSec":"8"
				},
				{
					"Monsters":
					[
						{
							"ID":"I_Orc",
							"PosX":"-0.12",
							"PosY":"0.1",
							"RID":"83000292"
						},
						{
							"ID":"I_Orc",
							"PosX":"0.12",
							"PosY":"0.1",
							"RID":"83000302"
						}
					],
					"TimeSec":"10"
				},
				{
					"Monsters":
					[
						{
							"ID":"I_Orc",
							"PosX":"-0.12",
							"PosY":"0.1",
							"RID":"83000293"
						},
						{
							"ID":"I_Orc",
							"PosX":"0.12",
							"PosY":"0.1",
							"RID":"83000303"
						}
					],
					"TimeSec":"12"
				},
				{
					"Monsters":
					[
						{
							"ID":"I_Orc",
							"PosX":"-0.12",
							"PosY":"0.1",
							"RID":"83000294"
						},
						{
							"ID":"I_Orc",
							"PosX":"0.12",
							"PosY":"0.1",
							"RID":"83000304"
						}
					],
					"TimeSec":"14"
				},
				{
					"Monsters":
					[
						{
							"ID":"I_Orc",
							"PosX":"-0.12",
							"PosY":"0.1",
							"RID":"83000295"
						},
						{
							"ID":"I_Orc",
							"PosX":"0.12",
							"PosY":"0.1",
							"RID":"83000305"
						}
					],
					"TimeSec":"16"
				},
				{
					"Monsters":
					[
						{
							"ID":"I_Orc",
							"PosX":"-0.12",
							"PosY":"0.1",
							"RID":"83000296"
						},
						{
							"ID":"I_Orc",
							"PosX":"0.12",
							"PosY":"0.1",
							"RID":"83000306"
						}
					],
					"TimeSec":"18"
				},
				{
					"Monsters":
					[
						{
							"ID":"I_Orc",
							"PosX":"-0.12",
							"PosY":"0.1",
							"RID":"83000297"
						},
						{
							"ID":"I_Orc",
							"PosX":"0.12",
							"PosY":"0.1",
							"RID":"83000307"
						}
					],
					"TimeSec":"20"
				},
				{
					"Monsters":
					[
						{
							"ID":"I_Orc",
							"PosX":"-0.12",
							"PosY":"0.1",
							"RID":"83000298"
						},
						{
							"ID":"I_Orc",
							"PosX":"0.12",
							"PosY":"0.1",
							"RID":"83000308"
						}
					],
					"TimeSec":"22"
				},
				{
					"Monsters":
					[
						{
							"ID":"I_Orc",
							"PosX":"-0.12",
							"PosY":"0.1",
							"RID":"83000299"
						},
						{
							"ID":"I_Orc",
							"PosX":"0.12",
							"PosY":"0.1",
							"RID":"83000309"
						}
					],
					"TimeSec":"24"
				}
			],
			"Title":"Untitled"
		},
		{
			"Events":
			[
				{
					"Scripts":
					[
						{
							"PosX":"0.036207",
							"PosY":"-0.146552",
							"TargetRID":"81000095",
							"Text":"animate count-idle"
						},
						{
							"PosX":"0.075862",
							"PosY":"0.063793",
							"TargetRID":"81000096",
							"Text":"animate count-idle"
						},
						{
							"PosX":"-0.101724",
							"PosY":"0.024138",
							"TargetRID":"81000097",
							"Text":"animate count-idle"
						}
					],
					"TimeSec":"0"
				},
				{
					"Monsters":
					[
						{
							"ID":"I_Orc",
							"PosX":"-0.44",
							"PosY":"-0.433333",
							"RID":"83000310"
						},
						{
							"ID":"I_Orc",
							"PosX":"0.44",
							"PosY":"-0.433333",
							"RID":"83000320"
						},
						{
							"ID":"I_Slime",
							"PosX":"0",
							"PosY":"-0.45",
							"RID":"83000330"
						}
					],
					"TimeSec":"6"
				},
				{
					"Monsters":
					[
						{
							"ID":"I_Orc",
							"PosX":"-0.44",
							"PosY":"-0.433333",
							"RID":"83000311"
						},
						{
							"ID":"I_Orc",
							"PosX":"0.44",
							"PosY":"-0.433333",
							"RID":"83000321"
						},
						{
							"ID":"I_Slime",
							"PosX":"0",
							"PosY":"-0.45",
							"RID":"83000331"
						}
					],
					"TimeSec":"7"
				},
				{
					"Monsters":
					[
						{
							"ID":"I_Orc",
							"PosX":"-0.44",
							"PosY":"-0.433333",
							"RID":"83000312"
						},
						{
							"ID":"I_Orc",
							"PosX":"0.44",
							"PosY":"-0.433333",
							"RID":"83000322"
						},
						{
							"ID":"I_Slime",
							"PosX":"0",
							"PosY":"-0.45",
							"RID":"83000332"
						}
					],
					"TimeSec":"8"
				},
				{
					"Monsters":
					[
						{
							"ID":"I_Orc",
							"PosX":"-0.44",
							"PosY":"-0.433333",
							"RID":"83000313"
						},
						{
							"ID":"I_Orc",
							"PosX":"0.44",
							"PosY":"-0.433333",
							"RID":"83000323"
						},
						{
							"ID":"I_Slime",
							"PosX":"0",
							"PosY":"-0.45",
							"RID":"83000333"
						}
					],
					"TimeSec":"9"
				},
				{
					"Monsters":
					[
						{
							"ID":"I_Orc",
							"PosX":"-0.44",
							"PosY":"-0.433333",
							"RID":"83000314"
						},
						{
							"ID":"I_Orc",
							"PosX":"0.44",
							"PosY":"-0.433333",
							"RID":"83000324"
						},
						{
							"ID":"I_Slime",
							"PosX":"0",
							"PosY":"-0.45",
							"RID":"83000334"
						}
					],
					"TimeSec":"10"
				},
				{
					"Monsters":
					[
						{
							"ID":"I_Orc",
							"PosX":"-0.44",
							"PosY":"-0.433333",
							"RID":"83000315"
						},
						{
							"ID":"I_Orc",
							"PosX":"0.44",
							"PosY":"-0.433333",
							"RID":"83000325"
						},
						{
							"ID":"I_Slime",
							"PosX":"0",
							"PosY":"-0.45",
							"RID":"83000335"
						}
					],
					"TimeSec":"11"
				},
				{
					"Monsters":
					[
						{
							"ID":"I_Orc",
							"PosX":"-0.44",
							"PosY":"-0.433333",
							"RID":"83000316"
						},
						{
							"ID":"I_Orc",
							"PosX":"0.44",
							"PosY":"-0.433333",
							"RID":"83000326"
						},
						{
							"ID":"I_Slime",
							"PosX":"0",
							"PosY":"-0.45",
							"RID":"83000336"
						}
					],
					"TimeSec":"12"
				},
				{
					"Monsters":
					[
						{
							"ID":"I_Orc",
							"PosX":"-0.44",
							"PosY":"-0.433333",
							"RID":"83000317"
						},
						{
							"ID":"I_Orc",
							"PosX":"0.44",
							"PosY":"-0.433333",
							"RID":"83000327"
						},
						{
							"ID":"I_Slime",
							"PosX":"0",
							"PosY":"-0.45",
							"RID":"83000337"
						}
					],
					"TimeSec":"13"
				},
				{
					"Monsters":
					[
						{
							"ID":"I_Orc",
							"PosX":"-0.44",
							"PosY":"-0.433333",
							"RID":"83000318"
						},
						{
							"ID":"I_Orc",
							"PosX":"0.44",
							"PosY":"-0.433333",
							"RID":"83000328"
						},
						{
							"ID":"I_Slime",
							"PosX":"0",
							"PosY":"-0.45",
							"RID":"83000338"
						}
					],
					"TimeSec":"14"
				},
				{
					"Monsters":
					[
						{
							"ID":"I_Orc",
							"PosX":"-0.44",
							"PosY":"-0.433333",
							"RID":"83000319"
						},
						{
							"ID":"I_Orc",
							"PosX":"0.44",
							"PosY":"-0.433333",
							"RID":"83000329"
						},
						{
							"ID":"I_Slime",
							"PosX":"0",
							"PosY":"-0.45",
							"RID":"83000339"
						}
					],
					"TimeSec":"15"
				},
				{
					"Monsters":
					[
						{
							"ID":"I_Wolf",
							"PosX":"0",
							"PosY":"-0.45",
							"RID":"83000340"
						},
						{
							"ID":"I_Wolf",
							"PosX":"-0.44",
							"PosY":"-0.433333",
							"RID":"83000350"
						},
						{
							"ID":"I_Wolf",
							"PosX":"0.44",
							"PosY":"-0.433333",
							"RID":"83000360"
						}
					],
					"TimeSec":"18"
				},
				{
					"Monsters":
					[
						{
							"ID":"I_Wolf",
							"PosX":"0",
							"PosY":"-0.45",
							"RID":"83000341"
						},
						{
							"ID":"I_Wolf",
							"PosX":"-0.44",
							"PosY":"-0.433333",
							"RID":"83000351"
						},
						{
							"ID":"I_Wolf",
							"PosX":"0.44",
							"PosY":"-0.433333",
							"RID":"83000361"
						}
					],
					"TimeSec":"20"
				},
				{
					"Monsters":
					[
						{
							"ID":"I_Wolf",
							"PosX":"0",
							"PosY":"-0.45",
							"RID":"83000342"
						},
						{
							"ID":"I_Wolf",
							"PosX":"-0.44",
							"PosY":"-0.433333",
							"RID":"83000352"
						},
						{
							"ID":"I_Wolf",
							"PosX":"0.44",
							"PosY":"-0.433333",
							"RID":"83000362"
						}
					],
					"TimeSec":"22"
				},
				{
					"Monsters":
					[
						{
							"ID":"I_Wolf",
							"PosX":"0",
							"PosY":"-0.45",
							"RID":"83000343"
						},
						{
							"ID":"I_Wolf",
							"PosX":"-0.44",
							"PosY":"-0.433333",
							"RID":"83000353"
						},
						{
							"ID":"I_Wolf",
							"PosX":"0.44",
							"PosY":"-0.433333",
							"RID":"83000363"
						}
					],
					"TimeSec":"24"
				},
				{
					"Monsters":
					[
						{
							"ID":"I_Wolf",
							"PosX":"0",
							"PosY":"-0.45",
							"RID":"83000344"
						},
						{
							"ID":"I_Wolf",
							"PosX":"-0.44",
							"PosY":"-0.433333",
							"RID":"83000354"
						},
						{
							"ID":"I_Wolf",
							"PosX":"0.44",
							"PosY":"-0.433333",
							"RID":"83000364"
						}
					],
					"TimeSec":"26"
				},
				{
					"Monsters":
					[
						{
							"ID":"I_Wolf",
							"PosX":"0",
							"PosY":"-0.45",
							"RID":"83000345"
						},
						{
							"ID":"I_Wolf",
							"PosX":"-0.44",
							"PosY":"-0.433333",
							"RID":"83000355"
						},
						{
							"ID":"I_Wolf",
							"PosX":"0.44",
							"PosY":"-0.433333",
							"RID":"83000365"
						}
					],
					"TimeSec":"28"
				},
				{
					"Monsters":
					[
						{
							"ID":"I_Wolf",
							"PosX":"0",
							"PosY":"-0.45",
							"RID":"83000346"
						},
						{
							"ID":"I_Wolf",
							"PosX":"-0.44",
							"PosY":"-0.433333",
							"RID":"83000356"
						},
						{
							"ID":"I_Wolf",
							"PosX":"0.44",
							"PosY":"-0.433333",
							"RID":"83000366"
						}
					],
					"TimeSec":"30"
				},
				{
					"Monsters":
					[
						{
							"ID":"I_Wolf",
							"PosX":"0",
							"PosY":"-0.45",
							"RID":"83000347"
						},
						{
							"ID":"I_Wolf",
							"PosX":"-0.44",
							"PosY":"-0.433333",
							"RID":"83000357"
						},
						{
							"ID":"I_Wolf",
							"PosX":"0.44",
							"PosY":"-0.433333",
							"RID":"83000367"
						}
					],
					"TimeSec":"32"
				},
				{
					"Monsters":
					[
						{
							"ID":"I_Wolf",
							"PosX":"0",
							"PosY":"-0.45",
							"RID":"83000348"
						},
						{
							"ID":"I_Wolf",
							"PosX":"-0.44",
							"PosY":"-0.433333",
							"RID":"83000358"
						},
						{
							"ID":"I_Wolf",
							"PosX":"0.44",
							"PosY":"-0.433333",
							"RID":"83000368"
						}
					],
					"TimeSec":"34"
				},
				{
					"Monsters":
					[
						{
							"ID":"I_Wolf",
							"PosX":"0",
							"PosY":"-0.45",
							"RID":"83000349"
						},
						{
							"ID":"I_Wolf",
							"PosX":"-0.44",
							"PosY":"-0.433333",
							"RID":"83000359"
						},
						{
							"ID":"I_Wolf",
							"PosX":"0.44",
							"PosY":"-0.433333",
							"RID":"83000369"
						}
					],
					"TimeSec":"36"
				},
				{
					"Monsters":
					[
						{
							"ID":"I_Orc",
							"PosX":"0.44",
							"PosY":"-0.433333",
							"RID":"83000370"
						},
						{
							"ID":"I_Orc",
							"PosX":"0",
							"PosY":"-0.45",
							"RID":"83000380"
						},
						{
							"ID":"I_Orc",
							"PosX":"-0.44",
							"PosY":"-0.433333",
							"RID":"83000390"
						}
					],
					"TimeSec":"39"
				},
				{
					"Monsters":
					[
						{
							"ID":"I_Slime",
							"PosX":"0.44",
							"PosY":"-0.433333",
							"RID":"83000371"
						},
						{
							"ID":"I_Slime",
							"PosX":"0",
							"PosY":"-0.45",
							"RID":"83000381"
						},
						{
							"ID":"I_Slime",
							"PosX":"-0.44",
							"PosY":"-0.433333",
							"RID":"83000391"
						}
					],
					"TimeSec":"41"
				},
				{
					"Monsters":
					[
						{
							"ID":"I_Orc",
							"PosX":"0.44",
							"PosY":"-0.433333",
							"RID":"83000372"
						},
						{
							"ID":"I_Orc",
							"PosX":"0",
							"PosY":"-0.45",
							"RID":"83000382"
						},
						{
							"ID":"I_Orc",
							"PosX":"-0.44",
							"PosY":"-0.433333",
							"RID":"83000392"
						}
					],
					"TimeSec":"43"
				},
				{
					"Monsters":
					[
						{
							"ID":"I_Slime",
							"PosX":"0.44",
							"PosY":"-0.433333",
							"RID":"83000373"
						},
						{
							"ID":"I_Slime",
							"PosX":"0",
							"PosY":"-0.45",
							"RID":"83000383"
						},
						{
							"ID":"I_Slime",
							"PosX":"-0.44",
							"PosY":"-0.433333",
							"RID":"83000393"
						}
					],
					"TimeSec":"45"
				},
				{
					"Monsters":
					[
						{
							"ID":"I_Orc",
							"PosX":"0.44",
							"PosY":"-0.433333",
							"RID":"83000374"
						},
						{
							"ID":"I_Orc",
							"PosX":"0",
							"PosY":"-0.45",
							"RID":"83000384"
						},
						{
							"ID":"I_Orc",
							"PosX":"-0.44",
							"PosY":"-0.433333",
							"RID":"83000394"
						}
					],
					"TimeSec":"47"
				},
				{
					"Monsters":
					[
						{
							"ID":"I_Slime",
							"PosX":"0.44",
							"PosY":"-0.433333",
							"RID":"83000375"
						},
						{
							"ID":"I_Slime",
							"PosX":"0",
							"PosY":"-0.45",
							"RID":"83000385"
						},
						{
							"ID":"I_Slime",
							"PosX":"-0.44",
							"PosY":"-0.433333",
							"RID":"83000395"
						}
					],
					"TimeSec":"49"
				},
				{
					"Monsters":
					[
						{
							"ID":"I_Orc",
							"PosX":"0.44",
							"PosY":"-0.433333",
							"RID":"83000376"
						},
						{
							"ID":"I_Orc",
							"PosX":"0",
							"PosY":"-0.45",
							"RID":"83000386"
						},
						{
							"ID":"I_Orc",
							"PosX":"-0.44",
							"PosY":"-0.433333",
							"RID":"83000396"
						}
					],
					"TimeSec":"51"
				},
				{
					"Monsters":
					[
						{
							"ID":"I_Slime",
							"PosX":"0.44",
							"PosY":"-0.433333",
							"RID":"83000377"
						},
						{
							"ID":"I_Slime",
							"PosX":"0",
							"PosY":"-0.45",
							"RID":"83000387"
						},
						{
							"ID":"I_Slime",
							"PosX":"-0.44",
							"PosY":"-0.433333",
							"RID":"83000397"
						}
					],
					"TimeSec":"53"
				},
				{
					"Monsters":
					[
						{
							"ID":"I_Orc",
							"PosX":"0.44",
							"PosY":"-0.433333",
							"RID":"83000378"
						},
						{
							"ID":"I_Orc",
							"PosX":"0",
							"PosY":"-0.45",
							"RID":"83000388"
						},
						{
							"ID":"I_Orc",
							"PosX":"-0.44",
							"PosY":"-0.433333",
							"RID":"83000398"
						}
					],
					"TimeSec":"55"
				},
				{
					"Monsters":
					[
						{
							"ID":"I_Slime",
							"PosX":"0.44",
							"PosY":"-0.433333",
							"RID":"83000379"
						},
						{
							"ID":"I_Slime",
							"PosX":"0",
							"PosY":"-0.45",
							"RID":"83000389"
						},
						{
							"ID":"I_Slime",
							"PosX":"-0.44",
							"PosY":"-0.433333",
							"RID":"83000399"
						}
					],
					"TimeSec":"57"
				}
			],
			"Title":"Untitled"
		},
		{
			"Events":
			[
				{
					"Scripts":
					[
						{
							"PosX":"0.017241",
							"PosY":"-0.125862",
							"TargetRID":"81000095",
							"Text":"animate count-idle"
						},
						{
							"PosX":"0.024138",
							"PosY":"-0.144828",
							"TargetRID":"81000096",
							"Text":"animate count-idle"
						},
						{
							"PosX":"0.001724",
							"PosY":"-0.172414",
							"TargetRID":"81000097",
							"Text":"animate count-idle"
						}
					],
					"TimeSec":"0"
				},
				{
					"Monsters":
					[
						{
							"ID":"I_Orc",
							"PosX":"-0.44",
							"PosY":"-0.433333",
							"RID":"83000400"
						},
						{
							"ID":"I_Orc",
							"PosX":"0",
							"PosY":"-0.45",
							"RID":"83000410"
						},
						{
							"ID":"I_Orc",
							"PosX":"0.44",
							"PosY":"-0.433333",
							"RID":"83000420"
						}
					],
					"TimeSec":"6"
				},
				{
					"Monsters":
					[
						{
							"ID":"I_Orc",
							"PosX":"-0.44",
							"PosY":"-0.433333",
							"RID":"83000401"
						},
						{
							"ID":"I_Orc",
							"PosX":"0",
							"PosY":"-0.45",
							"RID":"83000411"
						},
						{
							"ID":"I_Orc",
							"PosX":"0.44",
							"PosY":"-0.433333",
							"RID":"83000421"
						}
					],
					"TimeSec":"7"
				},
				{
					"Monsters":
					[
						{
							"ID":"I_Orc",
							"PosX":"-0.44",
							"PosY":"-0.433333",
							"RID":"83000402"
						},
						{
							"ID":"I_Orc",
							"PosX":"0",
							"PosY":"-0.45",
							"RID":"83000412"
						},
						{
							"ID":"I_Orc",
							"PosX":"0.44",
							"PosY":"-0.433333",
							"RID":"83000422"
						}
					],
					"TimeSec":"8"
				},
				{
					"Monsters":
					[
						{
							"ID":"I_Orc",
							"PosX":"-0.44",
							"PosY":"-0.433333",
							"RID":"83000403"
						},
						{
							"ID":"I_Orc",
							"PosX":"0",
							"PosY":"-0.45",
							"RID":"83000413"
						},
						{
							"ID":"I_Orc",
							"PosX":"0.44",
							"PosY":"-0.433333",
							"RID":"83000423"
						}
					],
					"TimeSec":"9"
				},
				{
					"Monsters":
					[
						{
							"ID":"I_Orc",
							"PosX":"-0.44",
							"PosY":"-0.433333",
							"RID":"83000404"
						},
						{
							"ID":"I_Orc",
							"PosX":"0",
							"PosY":"-0.45",
							"RID":"83000414"
						},
						{
							"ID":"I_Orc",
							"PosX":"0.44",
							"PosY":"-0.433333",
							"RID":"83000424"
						}
					],
					"TimeSec":"10"
				},
				{
					"Monsters":
					[
						{
							"ID":"I_Orc",
							"PosX":"-0.44",
							"PosY":"-0.433333",
							"RID":"83000405"
						},
						{
							"ID":"I_Orc",
							"PosX":"0",
							"PosY":"-0.45",
							"RID":"83000415"
						},
						{
							"ID":"I_Orc",
							"PosX":"0.44",
							"PosY":"-0.433333",
							"RID":"83000425"
						}
					],
					"TimeSec":"11"
				},
				{
					"Monsters":
					[
						{
							"ID":"I_Orc",
							"PosX":"-0.44",
							"PosY":"-0.433333",
							"RID":"83000406"
						},
						{
							"ID":"I_Orc",
							"PosX":"0",
							"PosY":"-0.45",
							"RID":"83000416"
						},
						{
							"ID":"I_Orc",
							"PosX":"0.44",
							"PosY":"-0.433333",
							"RID":"83000426"
						}
					],
					"TimeSec":"12"
				},
				{
					"Monsters":
					[
						{
							"ID":"I_Orc",
							"PosX":"-0.44",
							"PosY":"-0.433333",
							"RID":"83000407"
						},
						{
							"ID":"I_Orc",
							"PosX":"0",
							"PosY":"-0.45",
							"RID":"83000417"
						},
						{
							"ID":"I_Orc",
							"PosX":"0.44",
							"PosY":"-0.433333",
							"RID":"83000427"
						}
					],
					"TimeSec":"13"
				},
				{
					"Monsters":
					[
						{
							"ID":"I_Orc",
							"PosX":"-0.44",
							"PosY":"-0.433333",
							"RID":"83000408"
						},
						{
							"ID":"I_Orc",
							"PosX":"0",
							"PosY":"-0.45",
							"RID":"83000418"
						},
						{
							"ID":"I_Orc",
							"PosX":"0.44",
							"PosY":"-0.433333",
							"RID":"83000428"
						}
					],
					"TimeSec":"14"
				},
				{
					"Monsters":
					[
						{
							"ID":"I_Orc",
							"PosX":"-0.44",
							"PosY":"-0.433333",
							"RID":"83000409"
						},
						{
							"ID":"I_Orc",
							"PosX":"0",
							"PosY":"-0.45",
							"RID":"83000419"
						},
						{
							"ID":"I_Orc",
							"PosX":"0.44",
							"PosY":"-0.433333",
							"RID":"83000429"
						}
					],
					"TimeSec":"15"
				},
				{
					"Monsters":
					[
						{
							"ID":"I_Orc",
							"PosX":"-0.44",
							"PosY":"-0.433333",
							"RID":"83000430"
						},
						{
							"ID":"I_Orc",
							"PosX":"0",
							"PosY":"-0.45",
							"RID":"83000440"
						},
						{
							"ID":"I_Orc",
							"PosX":"0.44",
							"PosY":"-0.433333",
							"RID":"83000450"
						}
					],
					"TimeSec":"18"
				},
				{
					"Monsters":
					[
						{
							"ID":"I_Slime",
							"PosX":"-0.44",
							"PosY":"-0.433333",
							"RID":"83000431"
						},
						{
							"ID":"I_Slime",
							"PosX":"0",
							"PosY":"-0.45",
							"RID":"83000441"
						},
						{
							"ID":"I_Slime",
							"PosX":"0.44",
							"PosY":"-0.433333",
							"RID":"83000451"
						}
					],
					"TimeSec":"20"
				},
				{
					"Monsters":
					[
						{
							"ID":"I_Orc",
							"PosX":"-0.44",
							"PosY":"-0.433333",
							"RID":"83000432"
						},
						{
							"ID":"I_Orc",
							"PosX":"0",
							"PosY":"-0.45",
							"RID":"83000442"
						},
						{
							"ID":"I_Orc",
							"PosX":"0.44",
							"PosY":"-0.433333",
							"RID":"83000452"
						}
					],
					"TimeSec":"22"
				},
				{
					"Monsters":
					[
						{
							"ID":"I_Slime",
							"PosX":"-0.44",
							"PosY":"-0.433333",
							"RID":"83000433"
						},
						{
							"ID":"I_Slime",
							"PosX":"0",
							"PosY":"-0.45",
							"RID":"83000443"
						},
						{
							"ID":"I_Slime",
							"PosX":"0.44",
							"PosY":"-0.433333",
							"RID":"83000453"
						}
					],
					"TimeSec":"24"
				},
				{
					"Monsters":
					[
						{
							"ID":"I_Orc",
							"PosX":"-0.44",
							"PosY":"-0.433333",
							"RID":"83000434"
						},
						{
							"ID":"I_Orc",
							"PosX":"0",
							"PosY":"-0.45",
							"RID":"83000444"
						},
						{
							"ID":"I_Orc",
							"PosX":"0.44",
							"PosY":"-0.433333",
							"RID":"83000454"
						}
					],
					"TimeSec":"26"
				},
				{
					"Monsters":
					[
						{
							"ID":"I_Slime",
							"PosX":"-0.44",
							"PosY":"-0.433333",
							"RID":"83000435"
						},
						{
							"ID":"I_Slime",
							"PosX":"0",
							"PosY":"-0.45",
							"RID":"83000445"
						},
						{
							"ID":"I_Slime",
							"PosX":"0.44",
							"PosY":"-0.433333",
							"RID":"83000455"
						}
					],
					"TimeSec":"28"
				},
				{
					"Monsters":
					[
						{
							"ID":"I_Orc",
							"PosX":"-0.44",
							"PosY":"-0.433333",
							"RID":"83000436"
						},
						{
							"ID":"I_Orc",
							"PosX":"0",
							"PosY":"-0.45",
							"RID":"83000446"
						},
						{
							"ID":"I_Orc",
							"PosX":"0.44",
							"PosY":"-0.433333",
							"RID":"83000456"
						}
					],
					"TimeSec":"30"
				},
				{
					"Monsters":
					[
						{
							"ID":"I_Slime",
							"PosX":"-0.44",
							"PosY":"-0.433333",
							"RID":"83000437"
						},
						{
							"ID":"I_Slime",
							"PosX":"0",
							"PosY":"-0.45",
							"RID":"83000447"
						},
						{
							"ID":"I_Slime",
							"PosX":"0.44",
							"PosY":"-0.433333",
							"RID":"83000457"
						}
					],
					"TimeSec":"32"
				},
				{
					"Monsters":
					[
						{
							"ID":"I_Orc",
							"PosX":"-0.44",
							"PosY":"-0.433333",
							"RID":"83000438"
						},
						{
							"ID":"I_Orc",
							"PosX":"0",
							"PosY":"-0.45",
							"RID":"83000448"
						},
						{
							"ID":"I_Orc",
							"PosX":"0.44",
							"PosY":"-0.433333",
							"RID":"83000458"
						}
					],
					"TimeSec":"34"
				},
				{
					"Monsters":
					[
						{
							"ID":"I_Slime",
							"PosX":"-0.44",
							"PosY":"-0.433333",
							"RID":"83000439"
						},
						{
							"ID":"I_Slime",
							"PosX":"0",
							"PosY":"-0.45",
							"RID":"83000449"
						},
						{
							"ID":"I_Slime",
							"PosX":"0.44",
							"PosY":"-0.433333",
							"RID":"83000459"
						}
					],
					"TimeSec":"36"
				},
				{
					"Monsters":
					[
						{
							"ID":"I_Wolf",
							"PosX":"0",
							"PosY":"-0.45",
							"RID":"83000460"
						},
						{
							"ID":"I_Wolf",
							"PosX":"-0.44",
							"PosY":"-0.433333",
							"RID":"83000470"
						},
						{
							"ID":"I_Wolf",
							"PosX":"0.44",
							"PosY":"-0.433333",
							"RID":"83000480"
						}
					],
					"TimeSec":"39"
				},
				{
					"Monsters":
					[
						{
							"ID":"I_Wolf",
							"PosX":"0",
							"PosY":"-0.45",
							"RID":"83000461"
						},
						{
							"ID":"I_Wolf",
							"PosX":"-0.44",
							"PosY":"-0.433333",
							"RID":"83000471"
						},
						{
							"ID":"I_Wolf",
							"PosX":"0.44",
							"PosY":"-0.433333",
							"RID":"83000481"
						}
					],
					"TimeSec":"41"
				},
				{
					"Monsters":
					[
						{
							"ID":"I_Wolf",
							"PosX":"0",
							"PosY":"-0.45",
							"RID":"83000462"
						},
						{
							"ID":"I_Wolf",
							"PosX":"-0.44",
							"PosY":"-0.433333",
							"RID":"83000472"
						},
						{
							"ID":"I_Wolf",
							"PosX":"0.44",
							"PosY":"-0.433333",
							"RID":"83000482"
						}
					],
					"TimeSec":"43"
				},
				{
					"Monsters":
					[
						{
							"ID":"I_Wolf",
							"PosX":"0",
							"PosY":"-0.45",
							"RID":"83000463"
						},
						{
							"ID":"I_Wolf",
							"PosX":"-0.44",
							"PosY":"-0.433333",
							"RID":"83000473"
						},
						{
							"ID":"I_Wolf",
							"PosX":"0.44",
							"PosY":"-0.433333",
							"RID":"83000483"
						}
					],
					"TimeSec":"45"
				},
				{
					"Monsters":
					[
						{
							"ID":"I_Wolf",
							"PosX":"0",
							"PosY":"-0.45",
							"RID":"83000464"
						},
						{
							"ID":"I_Wolf",
							"PosX":"-0.44",
							"PosY":"-0.433333",
							"RID":"83000474"
						},
						{
							"ID":"I_Wolf",
							"PosX":"0.44",
							"PosY":"-0.433333",
							"RID":"83000484"
						}
					],
					"TimeSec":"47"
				},
				{
					"Monsters":
					[
						{
							"ID":"I_Wolf",
							"PosX":"0",
							"PosY":"-0.45",
							"RID":"83000465"
						},
						{
							"ID":"I_Wolf",
							"PosX":"-0.44",
							"PosY":"-0.433333",
							"RID":"83000475"
						},
						{
							"ID":"I_Wolf",
							"PosX":"0.44",
							"PosY":"-0.433333",
							"RID":"83000485"
						}
					],
					"TimeSec":"49"
				},
				{
					"Monsters":
					[
						{
							"ID":"I_Wolf",
							"PosX":"0",
							"PosY":"-0.45",
							"RID":"83000466"
						},
						{
							"ID":"I_Wolf",
							"PosX":"-0.44",
							"PosY":"-0.433333",
							"RID":"83000476"
						},
						{
							"ID":"I_Wolf",
							"PosX":"0.44",
							"PosY":"-0.433333",
							"RID":"83000486"
						}
					],
					"TimeSec":"51"
				},
				{
					"Monsters":
					[
						{
							"ID":"I_Wolf",
							"PosX":"0",
							"PosY":"-0.45",
							"RID":"83000467"
						},
						{
							"ID":"I_Wolf",
							"PosX":"-0.44",
							"PosY":"-0.433333",
							"RID":"83000477"
						},
						{
							"ID":"I_Wolf",
							"PosX":"0.44",
							"PosY":"-0.433333",
							"RID":"83000487"
						}
					],
					"TimeSec":"53"
				},
				{
					"Monsters":
					[
						{
							"ID":"I_Wolf",
							"PosX":"0",
							"PosY":"-0.45",
							"RID":"83000468"
						},
						{
							"ID":"I_Wolf",
							"PosX":"-0.44",
							"PosY":"-0.433333",
							"RID":"83000478"
						},
						{
							"ID":"I_Wolf",
							"PosX":"0.44",
							"PosY":"-0.433333",
							"RID":"83000488"
						}
					],
					"TimeSec":"55"
				},
				{
					"Monsters":
					[
						{
							"ID":"I_Wolf",
							"PosX":"0",
							"PosY":"-0.45",
							"RID":"83000469"
						},
						{
							"ID":"I_Wolf",
							"PosX":"-0.44",
							"PosY":"-0.433333",
							"RID":"83000479"
						},
						{
							"ID":"I_Wolf",
							"PosX":"0.44",
							"PosY":"-0.433333",
							"RID":"83000489"
						}
					],
					"TimeSec":"57"
				}
			],
			"Title":"Untitled"
		}
	]
}
