{
	"BuildNumber":"19",
	"MapName":"map_48",
	"MissionLastRID":"83999999",
	"MonsterLastRID":"83000563",
	"ToolType":"stagetool_f1",
	"ToolVersion":"2",
	"Waves":
	[
		{
			"Events":
			[
				{
					"Scripts":
					[
						{
							"PosX":"-0.028322",
							"PosY":"0.20915",
							"TargetRID":"81000161",
							"Text":"animate count-idle"
						},
						{
							"PosX":"-0.058824",
							"PosY":"-0.108932",
							"TargetRID":"81000389",
							"Text":"animate count-idle"
						},
						{
							"PosX":"0.026144",
							"PosY":"0.12854",
							"TargetRID":"81000391",
							"Text":"animate count-idle"
						},
						{
							"PosX":"0.017429",
							"PosY":"-0.108932",
							"TargetRID":"81000393",
							"Text":"animate count-idle"
						},
						{
							"PosX":"0.008715",
							"PosY":"0.189543",
							"TargetRID":"81000403",
							"Text":"animate showing-show"
						},
						{
							"PosX":"0",
							"PosY":"0.089325",
							"TargetRID":"81000404",
							"Text":"animate showing-show"
						},
						{
							"PosX":"0.002179",
							"PosY":"0.189542",
							"TargetRID":"81000406",
							"Text":"animate showing-show"
						},
						{
							"PosX":"-0.030501",
							"PosY":"0.119826",
							"TargetRID":"81000407",
							"Text":"animate showing-show"
						},
						{
							"PosX":"0.005929",
							"PosY":"0.094862",
							"TargetRID":"81000432",
							"Text":"animate showing-show"
						},
						{
							"PosX":"-0.005929",
							"PosY":"0.077075",
							"TargetRID":"81000433",
							"Text":"animate showing-show"
						},
						{
							"PosX":"-0.021739",
							"PosY":"0.124506",
							"TargetRID":"81000434",
							"Text":"animate showing-show"
						},
						{
							"PosX":"-0.031621",
							"PosY":"0.160079",
							"TargetRID":"81000435",
							"Text":"animate showing-show"
						}
					],
					"TimeSec":"0"
				},
				{
					"Monsters":
					[
						{
							"ID":"F_Middle",
							"PosX":"-0.16",
							"PosY":"0.35",
							"RID":"83000000"
						},
						{
							"ID":"F_Middle",
							"PosX":"0.16",
							"PosY":"0.35",
							"RID":"83000004"
						},
						{
							"ID":"F_Normal",
							"PosX":"-0.46",
							"PosY":"-0.45",
							"RID":"83000008"
						},
						{
							"ID":"F_Normal",
							"PosX":"0.46",
							"PosY":"-0.45",
							"RID":"83000013"
						}
					],
					"TimeSec":"6"
				},
				{
					"Monsters":
					[
						{
							"ID":"F_Middle",
							"PosX":"-0.16",
							"PosY":"0.35",
							"RID":"83000001"
						},
						{
							"ID":"F_Middle",
							"PosX":"0.16",
							"PosY":"0.35",
							"RID":"83000005"
						},
						{
							"ID":"F_Normal",
							"PosX":"-0.46",
							"PosY":"-0.45",
							"RID":"83000009"
						},
						{
							"ID":"F_Normal",
							"PosX":"0.46",
							"PosY":"-0.45",
							"RID":"83000014"
						}
					],
					"TimeSec":"8"
				},
				{
					"Monsters":
					[
						{
							"ID":"F_Middle",
							"PosX":"-0.16",
							"PosY":"0.35",
							"RID":"83000002"
						},
						{
							"ID":"F_Middle",
							"PosX":"0.16",
							"PosY":"0.35",
							"RID":"83000006"
						},
						{
							"ID":"F_Normal",
							"PosX":"-0.46",
							"PosY":"-0.45",
							"RID":"83000010"
						},
						{
							"ID":"F_Normal",
							"PosX":"0.46",
							"PosY":"-0.45",
							"RID":"83000015"
						}
					],
					"TimeSec":"10"
				},
				{
					"Monsters":
					[
						{
							"ID":"F_Middle",
							"PosX":"-0.16",
							"PosY":"0.35",
							"RID":"83000003"
						},
						{
							"ID":"F_Middle",
							"PosX":"0.16",
							"PosY":"0.35",
							"RID":"83000007"
						},
						{
							"ID":"F_Normal",
							"PosX":"-0.46",
							"PosY":"-0.45",
							"RID":"83000011"
						},
						{
							"ID":"F_Normal",
							"PosX":"0.46",
							"PosY":"-0.45",
							"RID":"83000016"
						}
					],
					"TimeSec":"12"
				},
				{
					"Monsters":
					[
						{
							"ID":"F_Normal",
							"PosX":"-0.46",
							"PosY":"-0.45",
							"RID":"83000012"
						},
						{
							"ID":"F_Normal",
							"PosX":"0.46",
							"PosY":"-0.45",
							"RID":"83000017"
						}
					],
					"TimeSec":"14"
				}
			],
			"Title":"Untitled"
		},
		{
			"Events":
			[
				{
					"Scripts":
					[
						{
							"PosX":"0.045752",
							"PosY":"0.08061",
							"TargetRID":"81000390",
							"Text":"animate count-idle"
						},
						{
							"PosX":"-0.028322",
							"PosY":"0.056645",
							"TargetRID":"81000392",
							"Text":"animate count-idle"
						}
					],
					"TimeSec":"0"
				},
				{
					"Monsters":
					[
						{
							"ID":"F_Normal_B",
							"PosX":"-0.2",
							"PosY":"-0.433333",
							"RID":"83000028"
						},
						{
							"ID":"F_Normal_B",
							"PosX":"0.2",
							"PosY":"-0.433333",
							"RID":"83000033"
						}
					],
					"TimeSec":"6"
				},
				{
					"Monsters":
					[
						{
							"ID":"F_Normal",
							"PosX":"-0.2",
							"PosY":"-0.433333",
							"RID":"83000029"
						},
						{
							"ID":"F_Normal",
							"PosX":"0.2",
							"PosY":"-0.433333",
							"RID":"83000034"
						}
					],
					"TimeSec":"8"
				},
				{
					"Monsters":
					[
						{
							"ID":"F_Normal",
							"PosX":"-0.2",
							"PosY":"-0.433333",
							"RID":"83000030"
						},
						{
							"ID":"F_Normal",
							"PosX":"0.2",
							"PosY":"-0.433333",
							"RID":"83000035"
						}
					],
					"TimeSec":"10"
				},
				{
					"Monsters":
					[
						{
							"ID":"F_Normal",
							"PosX":"-0.2",
							"PosY":"-0.433333",
							"RID":"83000031"
						},
						{
							"ID":"F_Normal",
							"PosX":"0.2",
							"PosY":"-0.433333",
							"RID":"83000036"
						}
					],
					"TimeSec":"12"
				},
				{
					"Monsters":
					[
						{
							"ID":"F_Normal",
							"PosX":"-0.2",
							"PosY":"-0.433333",
							"RID":"83000032"
						},
						{
							"ID":"F_Normal",
							"PosX":"0.2",
							"PosY":"-0.433333",
							"RID":"83000037"
						}
					],
					"TimeSec":"14"
				}
			],
			"Title":"Untitled"
		},
		{
			"Events":
			[
				{
					"Scripts":
					[
						{
							"PosX":"0.028571",
							"PosY":"0.067347",
							"TargetRID":"81000161",
							"Text":"animate count-idle"
						},
						{
							"PosX":"-0.004082",
							"PosY":"-0.044898",
							"TargetRID":"81000388",
							"Text":"animate count-idle"
						},
						{
							"PosX":"0.006122",
							"PosY":"0.044898",
							"TargetRID":"81000391",
							"Text":"animate count-idle"
						}
					],
					"TimeSec":"5"
				},
				{
					"Monsters":
					[
						{
							"ID":"F_MiddleBoss",
							"PosX":"0",
							"PosY":"0.232945",
							"RID":"83000494"
						},
						{
							"ID":"F_Normal_B",
							"PosX":"-0.16",
							"PosY":"0.349418",
							"RID":"83000499"
						},
						{
							"ID":"F_Normal_B",
							"PosX":"0.16",
							"PosY":"0.349418",
							"RID":"83000500"
						}
					],
					"TimeSec":"11"
				},
				{
					"Monsters":
					[
						{
							"ID":"F_Middle",
							"PosX":"0",
							"PosY":"0.232945",
							"RID":"83000495"
						},
						{
							"ID":"F_Normal",
							"PosX":"-0.16",
							"PosY":"0.349418",
							"RID":"83000501"
						},
						{
							"ID":"F_Normal",
							"PosX":"0.16",
							"PosY":"0.349418",
							"RID":"83000502"
						}
					],
					"TimeSec":"13"
				},
				{
					"Monsters":
					[
						{
							"ID":"F_Middle",
							"PosX":"0",
							"PosY":"0.232945",
							"RID":"83000496"
						},
						{
							"ID":"F_Normal",
							"PosX":"-0.16",
							"PosY":"0.349418",
							"RID":"83000503"
						},
						{
							"ID":"F_Normal",
							"PosX":"0.16",
							"PosY":"0.349418",
							"RID":"83000504"
						}
					],
					"TimeSec":"15"
				},
				{
					"Monsters":
					[
						{
							"ID":"F_Middle",
							"PosX":"0",
							"PosY":"0.232945",
							"RID":"83000497"
						},
						{
							"ID":"F_Normal",
							"PosX":"-0.16",
							"PosY":"0.349418",
							"RID":"83000505"
						},
						{
							"ID":"F_Normal",
							"PosX":"0.16",
							"PosY":"0.349418",
							"RID":"83000506"
						}
					],
					"TimeSec":"17"
				},
				{
					"Monsters":
					[
						{
							"ID":"F_Middle",
							"PosX":"0",
							"PosY":"0.232945",
							"RID":"83000498"
						}
					],
					"TimeSec":"19"
				}
			],
			"Title":"Untitled"
		},
		{
			"Events":
			[
				{
					"Scripts":
					[
						{
							"PosX":"0.004082",
							"PosY":"0.081633",
							"TargetRID":"81000389",
							"Text":"animate count-idle"
						},
						{
							"PosX":"-0.134694",
							"PosY":"0.018367",
							"TargetRID":"81000390",
							"Text":"animate count-idle"
						},
						{
							"PosX":"0.157143",
							"PosY":"0.030612",
							"TargetRID":"81000392",
							"Text":"animate count-idle"
						},
						{
							"PosX":"-0.006122",
							"PosY":"-0.079592",
							"TargetRID":"81000393",
							"Text":"animate count-idle"
						}
					],
					"TimeSec":"5"
				},
				{
					"Monsters":
					[
						{
							"ID":"F_Normal_B",
							"PosX":"-0.46",
							"PosY":"-0.449251",
							"RID":"83000509"
						},
						{
							"ID":"F_Normal_B",
							"PosX":"0.46",
							"PosY":"-0.449251",
							"RID":"83000514"
						},
						{
							"ID":"F_Middle_B",
							"PosX":"0.2",
							"PosY":"-0.432612",
							"RID":"83000522"
						},
						{
							"ID":"F_Middle_B",
							"PosX":"-0.2",
							"PosY":"-0.432612",
							"RID":"83000523"
						}
					],
					"TimeSec":"11"
				},
				{
					"Monsters":
					[
						{
							"ID":"F_Normal_B",
							"PosX":"-0.46",
							"PosY":"-0.449251",
							"RID":"83000510"
						},
						{
							"ID":"F_Normal_B",
							"PosX":"0.46",
							"PosY":"-0.449251",
							"RID":"83000515"
						},
						{
							"ID":"F_Middle_B",
							"PosX":"0.2",
							"PosY":"-0.432612",
							"RID":"83000521"
						},
						{
							"ID":"F_Middle_B",
							"PosX":"-0.2",
							"PosY":"-0.432612",
							"RID":"83000524"
						}
					],
					"TimeSec":"13"
				},
				{
					"Monsters":
					[
						{
							"ID":"F_Normal_B",
							"PosX":"-0.46",
							"PosY":"-0.449251",
							"RID":"83000511"
						},
						{
							"ID":"F_Normal_B",
							"PosX":"0.46",
							"PosY":"-0.449251",
							"RID":"83000516"
						},
						{
							"ID":"F_Middle_B",
							"PosX":"0.2",
							"PosY":"-0.432612",
							"RID":"83000520"
						},
						{
							"ID":"F_Middle_B",
							"PosX":"-0.2",
							"PosY":"-0.432612",
							"RID":"83000525"
						}
					],
					"TimeSec":"15"
				},
				{
					"Monsters":
					[
						{
							"ID":"F_Normal_B",
							"PosX":"-0.46",
							"PosY":"-0.449251",
							"RID":"83000512"
						},
						{
							"ID":"F_Normal_B",
							"PosX":"0.46",
							"PosY":"-0.449251",
							"RID":"83000517"
						},
						{
							"ID":"F_Middle_B",
							"PosX":"0.2",
							"PosY":"-0.432612",
							"RID":"83000519"
						},
						{
							"ID":"F_Middle_B",
							"PosX":"-0.2",
							"PosY":"-0.432612",
							"RID":"83000526"
						}
					],
					"TimeSec":"17"
				},
				{
					"Monsters":
					[
						{
							"ID":"F_Normal_B",
							"PosX":"-0.46",
							"PosY":"-0.449251",
							"RID":"83000513"
						},
						{
							"ID":"F_Normal_B",
							"PosX":"0.46",
							"PosY":"-0.449251",
							"RID":"83000518"
						}
					],
					"TimeSec":"19"
				}
			],
			"Title":"Untitled"
		},
		{
			"Events":
			[
				{
					"Scripts":
					[
						{
							"PosX":"0.035382",
							"PosY":"0.132216",
							"TargetRID":"81000161",
							"Text":"animate count-idle"
						},
						{
							"PosX":"0.005587",
							"PosY":"0.048417",
							"TargetRID":"81000389",
							"Text":"animate count-idle"
						},
						{
							"PosX":"0.001862",
							"PosY":"0.083799",
							"TargetRID":"81000391",
							"Text":"animate count-idle"
						},
						{
							"PosX":"-0.024209",
							"PosY":"0.061453",
							"TargetRID":"81000393",
							"Text":"animate count-idle"
						}
					],
					"TimeSec":"5"
				},
				{
					"Monsters":
					[
						{
							"ID":"F_Normal_B",
							"PosX":"0.46",
							"PosY":"-0.449625",
							"RID":"83000331"
						},
						{
							"ID":"F_Normal_B",
							"PosX":"-0.46",
							"PosY":"-0.449625",
							"RID":"83000336"
						},
						{
							"ID":"F_Middle",
							"PosX":"-0.16",
							"PosY":"0.349418",
							"RID":"83000559"
						},
						{
							"ID":"F_Middle",
							"PosX":"0.16",
							"PosY":"0.349418",
							"RID":"83000561"
						}
					],
					"Scripts":
					[
						{
							"PosX":"0.007449",
							"PosY":"0.098696",
							"TargetRID":"81000432",
							"Text":"animate hiding-idle"
						},
						{
							"PosX":"-0.011173",
							"PosY":"0.05959",
							"TargetRID":"81000433",
							"Text":"animate hiding-idle"
						},
						{
							"PosX":"0",
							"PosY":"0.111732",
							"TargetRID":"81000434",
							"Text":"animate hiding-idle"
						},
						{
							"PosX":"0.001862",
							"PosY":"0.061453",
							"TargetRID":"81000435",
							"Text":"animate hiding-idle"
						}
					],
					"TimeSec":"11"
				},
				{
					"Monsters":
					[
						{
							"ID":"F_Normal",
							"PosX":"0.46",
							"PosY":"-0.449625",
							"RID":"83000332"
						},
						{
							"ID":"F_Normal",
							"PosX":"-0.46",
							"PosY":"-0.449625",
							"RID":"83000337"
						},
						{
							"ID":"F_Middle",
							"PosX":"-0.16",
							"PosY":"0.349709",
							"RID":"83000346"
						},
						{
							"ID":"F_Middle",
							"PosX":"0.16",
							"PosY":"0.349418",
							"RID":"83000560"
						}
					],
					"TimeSec":"13"
				},
				{
					"Monsters":
					[
						{
							"ID":"F_Normal",
							"PosX":"0.46",
							"PosY":"-0.449625",
							"RID":"83000333"
						},
						{
							"ID":"F_Normal",
							"PosX":"-0.46",
							"PosY":"-0.449625",
							"RID":"83000338"
						},
						{
							"ID":"F_Middle",
							"PosX":"0.16",
							"PosY":"0.349418",
							"RID":"83000562"
						},
						{
							"ID":"F_Middle",
							"PosX":"-0.16",
							"PosY":"0.349418",
							"RID":"83000563"
						}
					],
					"TimeSec":"15"
				},
				{
					"Monsters":
					[
						{
							"ID":"F_Normal",
							"PosX":"0.46",
							"PosY":"-0.449625",
							"RID":"83000334"
						},
						{
							"ID":"F_Normal",
							"PosX":"-0.46",
							"PosY":"-0.449625",
							"RID":"83000339"
						}
					],
					"TimeSec":"17"
				}
			],
			"Title":"Untitled"
		},
		{
			"Events":
			[
				{
					"Scripts":
					[
						{
							"PosX":"0.011173",
							"PosY":"-0.080074",
							"TargetRID":"81000388",
							"Text":"animate count-idle"
						},
						{
							"PosX":"0.005587",
							"PosY":"0.048417",
							"TargetRID":"81000390",
							"Text":"animate count-idle"
						},
						{
							"PosX":"0.083799",
							"PosY":"0.029795",
							"TargetRID":"81000392",
							"Text":"animate count-idle"
						}
					],
					"TimeSec":"5"
				},
				{
					"Monsters":
					[
						{
							"ID":"F_Middle",
							"PosX":"-0.2",
							"PosY":"-0.432973",
							"RID":"83000328"
						},
						{
							"ID":"F_Middle",
							"PosX":"0.2",
							"PosY":"-0.432973",
							"RID":"83000329"
						},
						{
							"ID":"F_MiddleBoss",
							"PosX":"0",
							"PosY":"0.233139",
							"RID":"83000330"
						}
					],
					"TimeSec":"11"
				},
				{
					"Monsters":
					[
						{
							"ID":"F_Middle",
							"PosX":"0",
							"PosY":"0.233139",
							"RID":"83000274"
						},
						{
							"ID":"F_Fast",
							"PosX":"-0.2",
							"PosY":"-0.432973",
							"RID":"83000278"
						},
						{
							"ID":"F_Fast",
							"PosX":"0.2",
							"PosY":"-0.432973",
							"RID":"83000281"
						}
					],
					"TimeSec":"13"
				},
				{
					"Monsters":
					[
						{
							"ID":"F_Middle",
							"PosX":"0",
							"PosY":"0.233139",
							"RID":"83000275"
						},
						{
							"ID":"F_Fast",
							"PosX":"-0.2",
							"PosY":"-0.432973",
							"RID":"83000279"
						},
						{
							"ID":"F_Fast",
							"PosX":"0.2",
							"PosY":"-0.432973",
							"RID":"83000282"
						}
					],
					"TimeSec":"15"
				}
			],
			"Title":"Untitled"
		},
		{
			"Events":
			[
				{
					"Scripts":
					[
						{
							"PosX":"-0.028958",
							"PosY":"0.07722",
							"TargetRID":"81000161",
							"Text":"animate count-idle"
						},
						{
							"PosX":"0.050193",
							"PosY":"-0.111969",
							"TargetRID":"81000389",
							"Text":"animate count-idle"
						},
						{
							"PosX":"0",
							"PosY":"0.057915",
							"TargetRID":"81000391",
							"Text":"animate count-idle"
						},
						{
							"PosX":"0.046332",
							"PosY":"-0.110039",
							"TargetRID":"81000393",
							"Text":"animate count-idle"
						}
					],
					"TimeSec":"10"
				},
				{
					"Monsters":
					[
						{
							"ID":"F_Middle_B",
							"PosX":"-0.46",
							"PosY":"-0.45",
							"RID":"83000411"
						},
						{
							"ID":"F_Middle_B",
							"PosX":"0.46",
							"PosY":"-0.45",
							"RID":"83000412"
						},
						{
							"ID":"F_Normal_B",
							"PosX":"-0.16",
							"PosY":"0.349418",
							"RID":"83000535"
						},
						{
							"ID":"F_Normal_B",
							"PosX":"0.16",
							"PosY":"0.349418",
							"RID":"83000536"
						}
					],
					"TimeSec":"16"
				},
				{
					"Monsters":
					[
						{
							"ID":"F_Normal_B",
							"PosX":"-0.46",
							"PosY":"-0.45",
							"RID":"83000415"
						},
						{
							"ID":"F_Normal_B",
							"PosX":"0.46",
							"PosY":"-0.45",
							"RID":"83000416"
						},
						{
							"ID":"F_Normal",
							"PosX":"-0.16",
							"PosY":"0.349418",
							"RID":"83000537"
						},
						{
							"ID":"F_Normal",
							"PosX":"0.16",
							"PosY":"0.349418",
							"RID":"83000538"
						}
					],
					"TimeSec":"18"
				},
				{
					"Monsters":
					[
						{
							"ID":"F_Middle_B",
							"PosX":"-0.46",
							"PosY":"-0.45",
							"RID":"83000419"
						},
						{
							"ID":"F_Middle_B",
							"PosX":"0.46",
							"PosY":"-0.45",
							"RID":"83000420"
						},
						{
							"ID":"F_Normal",
							"PosX":"-0.16",
							"PosY":"0.349418",
							"RID":"83000528"
						},
						{
							"ID":"F_Normal",
							"PosX":"0.16",
							"PosY":"0.349418",
							"RID":"83000529"
						}
					],
					"TimeSec":"20"
				},
				{
					"Monsters":
					[
						{
							"ID":"F_Normal_B",
							"PosX":"-0.46",
							"PosY":"-0.45",
							"RID":"83000425"
						},
						{
							"ID":"F_Normal_B",
							"PosX":"0.46",
							"PosY":"-0.45",
							"RID":"83000426"
						}
					],
					"TimeSec":"22"
				}
			],
			"Title":"Untitled"
		},
		{
			"Events":
			[
				{
					"Scripts":
					[
						{
							"PosX":"0.008163",
							"PosY":"0.059184",
							"TargetRID":"81000161",
							"Text":"animate count-idle"
						},
						{
							"PosX":"-0.012245",
							"PosY":"0.069388",
							"TargetRID":"81000390",
							"Text":"animate count-idle"
						},
						{
							"PosX":"0.004082",
							"PosY":"0.046939",
							"TargetRID":"81000391",
							"Text":"animate count-idle"
						},
						{
							"PosX":"0.102041",
							"PosY":"0.020408",
							"TargetRID":"81000392",
							"Text":"animate count-idle"
						}
					],
					"TimeSec":"10"
				},
				{
					"Monsters":
					[
						{
							"ID":"F_Normal_B",
							"PosX":"-0.2",
							"PosY":"-0.432612",
							"RID":"83000539"
						},
						{
							"ID":"F_Normal_B",
							"PosX":"0.2",
							"PosY":"-0.432612",
							"RID":"83000540"
						},
						{
							"ID":"F_Normal_B",
							"PosX":"-0.16",
							"PosY":"0.349418",
							"RID":"83000541"
						},
						{
							"ID":"F_Normal_B",
							"PosX":"0.16",
							"PosY":"0.349418",
							"RID":"83000542"
						}
					],
					"TimeSec":"16"
				},
				{
					"Monsters":
					[
						{
							"ID":"F_Normal",
							"PosX":"-0.2",
							"PosY":"-0.432612",
							"RID":"83000543"
						},
						{
							"ID":"F_Normal",
							"PosX":"0.2",
							"PosY":"-0.432612",
							"RID":"83000544"
						},
						{
							"ID":"F_Normal",
							"PosX":"-0.16",
							"PosY":"0.349418",
							"RID":"83000546"
						},
						{
							"ID":"F_Normal",
							"PosX":"0.16",
							"PosY":"0.349418",
							"RID":"83000548"
						}
					],
					"TimeSec":"18"
				},
				{
					"Monsters":
					[
						{
							"ID":"F_Normal",
							"PosX":"0.16",
							"PosY":"0.349418",
							"RID":"83000549"
						},
						{
							"ID":"F_Normal",
							"PosX":"-0.16",
							"PosY":"0.349418",
							"RID":"83000550"
						},
						{
							"ID":"F_Normal",
							"PosX":"-0.2",
							"PosY":"-0.432612",
							"RID":"83000551"
						},
						{
							"ID":"F_Normal",
							"PosX":"0.2",
							"PosY":"-0.432612",
							"RID":"83000552"
						}
					],
					"TimeSec":"20"
				},
				{
					"Monsters":
					[
						{
							"ID":"F_Normal",
							"PosX":"0.16",
							"PosY":"0.349418",
							"RID":"83000553"
						},
						{
							"ID":"F_Normal",
							"PosX":"-0.16",
							"PosY":"0.349418",
							"RID":"83000554"
						},
						{
							"ID":"F_Normal",
							"PosX":"-0.2",
							"PosY":"-0.432612",
							"RID":"83000555"
						},
						{
							"ID":"F_Normal",
							"PosX":"0.2",
							"PosY":"-0.432612",
							"RID":"83000556"
						}
					],
					"TimeSec":"22"
				}
			],
			"Title":"Untitled"
		},
		{
			"Events":
			[
				{
					"Scripts":
					[
						{
							"PosX":"0.001916",
							"PosY":"-0.044061",
							"TargetRID":"81000388",
							"Text":"animate count-idle"
						},
						{
							"PosX":"0.025692",
							"PosY":"0.06917",
							"TargetRID":"81000389",
							"Text":"animate count-idle"
						},
						{
							"PosX":"-0.009881",
							"PosY":"0.043478",
							"TargetRID":"81000393",
							"Text":"animate count-idle"
						}
					],
					"TimeSec":"10"
				},
				{
					"Monsters":
					[
						{
							"ID":"F_MiddleBoss",
							"PosX":"-0.46",
							"PosY":"-0.449625",
							"RID":"83000200"
						},
						{
							"ID":"F_MiddleBoss",
							"PosX":"0.46",
							"PosY":"-0.449625",
							"RID":"83000203"
						},
						{
							"ID":"F_Middle",
							"PosX":"0",
							"PosY":"0.232945",
							"RID":"83000557"
						}
					],
					"TimeSec":"16"
				},
				{
					"Monsters":
					[
						{
							"ID":"F_Middle",
							"PosX":"0.46",
							"PosY":"-0.449625",
							"RID":"83000227"
						},
						{
							"ID":"F_Middle",
							"PosX":"-0.46",
							"PosY":"-0.449625",
							"RID":"83000231"
						},
						{
							"ID":"F_Middle",
							"PosX":"0",
							"PosY":"0.233139",
							"RID":"83000491"
						}
					],
					"TimeSec":"18"
				},
				{
					"Monsters":
					[
						{
							"ID":"F_Fast",
							"PosX":"-0.46",
							"PosY":"-0.45",
							"RID":"83000409"
						},
						{
							"ID":"F_Fast",
							"PosX":"0.46",
							"PosY":"-0.45",
							"RID":"83000410"
						},
						{
							"ID":"F_Middle",
							"PosX":"0",
							"PosY":"0.233139",
							"RID":"83000492"
						}
					],
					"TimeSec":"20"
				},
				{
					"Monsters":
					[
						{
							"ID":"F_Fast",
							"PosX":"0.46",
							"PosY":"-0.45",
							"RID":"83000407"
						},
						{
							"ID":"F_Fast",
							"PosX":"-0.46",
							"PosY":"-0.45",
							"RID":"83000408"
						},
						{
							"ID":"F_Middle",
							"PosX":"0",
							"PosY":"0.232945",
							"RID":"83000558"
						}
					],
					"TimeSec":"22"
				}
			],
			"Title":"Untitled"
		},
		{
			"Events":
			[
				{
					"Scripts":
					[
						{
							"PosX":"0.019157",
							"PosY":"-0.130268",
							"TargetRID":"81000388",
							"Text":"animate count-idle"
						},
						{
							"PosX":"0.034483",
							"PosY":"0.08046",
							"TargetRID":"81000389",
							"Text":"animate count-idle"
						},
						{
							"PosX":"-0.005747",
							"PosY":"0.103448",
							"TargetRID":"81000393",
							"Text":"animate count-idle"
						}
					],
					"TimeSec":"10"
				},
				{
					"Monsters":
					[
						{
							"ID":"F_FinalBoss",
							"PosX":"-0.46",
							"PosY":"-0.449625",
							"RID":"83000431"
						},
						{
							"ID":"F_FinalBoss",
							"PosX":"0.46",
							"PosY":"-0.449625",
							"RID":"83000432"
						},
						{
							"ID":"F_FinalBoss",
							"PosX":"0",
							"PosY":"0.233139",
							"RID":"83000433"
						}
					],
					"TimeSec":"15"
				},
				{
					"Monsters":
					[
						{
							"ID":"F_Middle_B",
							"PosX":"-0.46",
							"PosY":"-0.449625",
							"RID":"83000434"
						},
						{
							"ID":"F_Middle_B",
							"PosX":"0.46",
							"PosY":"-0.449625",
							"RID":"83000435"
						},
						{
							"ID":"F_Middle_B",
							"PosX":"0",
							"PosY":"0.233139",
							"RID":"83000436"
						}
					],
					"TimeSec":"17"
				},
				{
					"Monsters":
					[
						{
							"ID":"F_Middle_B",
							"PosX":"0",
							"PosY":"0.233139",
							"RID":"83000437"
						},
						{
							"ID":"F_Middle_B",
							"PosX":"0.46",
							"PosY":"-0.449625",
							"RID":"83000438"
						},
						{
							"ID":"F_Middle_B",
							"PosX":"-0.46",
							"PosY":"-0.449625",
							"RID":"83000439"
						}
					],
					"TimeSec":"19"
				},
				{
					"Monsters":
					[
						{
							"ID":"F_Middle_B",
							"PosX":"-0.46",
							"PosY":"-0.449625",
							"RID":"83000440"
						},
						{
							"ID":"F_Middle_B",
							"PosX":"0.46",
							"PosY":"-0.449625",
							"RID":"83000442"
						},
						{
							"ID":"F_Middle_B",
							"PosX":"0",
							"PosY":"0.233139",
							"RID":"83000443"
						}
					],
					"TimeSec":"21"
				}
			],
			"Title":"Untitled"
		}
	]
}
