{
	"BuildNumber":"15",
	"MapName":"map_26",
	"MissionLastRID":"83999999",
	"MonsterLastRID":"83000605",
	"ToolType":"stagetool_f1",
	"ToolVersion":"2",
	"Waves":
	[
		{
			"Events":
			[
				{
					"Scripts":
					[
						{
							"PosX":"0",
							"PosY":"0.001799",
							"TargetRID":"81000230",
							"Text":"animate count-idle"
						},
						{
							"PosX":"-0.051852",
							"PosY":"0.083333",
							"TargetRID":"81000234",
							"Text":"animate count-idle"
						},
						{
							"PosX":"0",
							"PosY":"0",
							"TargetRID":"81000250",
							"Text":"animate count-idle"
						}
					],
					"TimeSec":"0"
				},
				{
					"Monsters":
					[
						{
							"ID":"F_Normal_B",
							"PosX":"-0.44",
							"PosY":"-0.449625",
							"RID":"83000000"
						}
					],
					"TimeSec":"6"
				},
				{
					"Monsters":
					[
						{
							"ID":"F_Normal",
							"PosX":"-0.44",
							"PosY":"-0.449625",
							"RID":"83000002"
						}
					],
					"TimeSec":"8"
				},
				{
					"Monsters":
					[
						{
							"ID":"F_Normal_B",
							"PosX":"-0.44",
							"PosY":"-0.449625",
							"RID":"83000003"
						}
					],
					"TimeSec":"10"
				},
				{
					"Monsters":
					[
						{
							"ID":"F_Normal",
							"PosX":"-0.44",
							"PosY":"-0.449625",
							"RID":"83000004"
						}
					],
					"TimeSec":"12"
				},
				{
					"Monsters":
					[
						{
							"ID":"F_Normal_B",
							"PosX":"-0.44",
							"PosY":"-0.449625",
							"RID":"83000005"
						}
					],
					"TimeSec":"14"
				},
				{
					"Monsters":
					[
						{
							"ID":"F_Normal",
							"PosX":"-0.44",
							"PosY":"-0.449625",
							"RID":"83000006"
						}
					],
					"TimeSec":"16"
				},
				{
					"Monsters":
					[
						{
							"ID":"F_Normal_B",
							"PosX":"-0.44",
							"PosY":"-0.449625",
							"RID":"83000007"
						}
					],
					"TimeSec":"18"
				}
			],
			"Title":"Untitled"
		},
		{
			"Events":
			[
				{
					"Scripts":
					[
						{
							"PosX":"0.007194",
							"PosY":"-0.19964",
							"TargetRID":"81000227",
							"Text":"animate count-idle"
						}
					],
					"TimeSec":"0"
				},
				{
					"Monsters":
					[
						{
							"ID":"F_Middle_B",
							"PosX":"-0.3",
							"PosY":"0.233139",
							"RID":"83000434"
						}
					],
					"TimeSec":"6"
				},
				{
					"Monsters":
					[
						{
							"ID":"F_Middle",
							"PosX":"-0.3",
							"PosY":"0.233139",
							"RID":"83000435"
						}
					],
					"TimeSec":"8"
				},
				{
					"Monsters":
					[
						{
							"ID":"F_Middle_B",
							"PosX":"-0.3",
							"PosY":"0.233139",
							"RID":"83000436"
						}
					],
					"TimeSec":"10"
				},
				{
					"Monsters":
					[
						{
							"ID":"F_Middle",
							"PosX":"-0.3",
							"PosY":"0.233139",
							"RID":"83000437"
						}
					],
					"TimeSec":"12"
				},
				{
					"Monsters":
					[
						{
							"ID":"F_Middle_B",
							"PosX":"-0.3",
							"PosY":"0.233139",
							"RID":"83000438"
						}
					],
					"TimeSec":"14"
				},
				{
					"Monsters":
					[
						{
							"ID":"F_Middle",
							"PosX":"-0.3",
							"PosY":"0.233139",
							"RID":"83000439"
						}
					],
					"TimeSec":"16"
				}
			],
			"Title":"Untitled"
		},
		{
			"Events":
			[
				{
					"Scripts":
					[
						{
							"PosX":"0.181481",
							"PosY":"-0.218519",
							"TargetRID":"81000231",
							"Text":"animate count-idle"
						},
						{
							"PosX":"0",
							"PosY":"0",
							"TargetRID":"81000249",
							"Text":"animate count-idle"
						}
					],
					"TimeSec":"0"
				},
				{
					"Monsters":
					[
						{
							"ID":"F_Middle_B",
							"PosX":"-0.3",
							"PosY":"-0.233139",
							"RID":"83000446"
						}
					],
					"TimeSec":"6"
				},
				{
					"Monsters":
					[
						{
							"ID":"F_Middle_B",
							"PosX":"-0.3",
							"PosY":"-0.233139",
							"RID":"83000447"
						}
					],
					"TimeSec":"8"
				},
				{
					"Monsters":
					[
						{
							"ID":"F_Middle_B",
							"PosX":"-0.3",
							"PosY":"-0.233139",
							"RID":"83000448"
						}
					],
					"TimeSec":"10"
				},
				{
					"Monsters":
					[
						{
							"ID":"F_Middle_B",
							"PosX":"-0.3",
							"PosY":"-0.233139",
							"RID":"83000449"
						}
					],
					"TimeSec":"12"
				},
				{
					"Monsters":
					[
						{
							"ID":"F_Middle_B",
							"PosX":"-0.3",
							"PosY":"-0.233139",
							"RID":"83000450"
						}
					],
					"TimeSec":"14"
				},
				{
					"Monsters":
					[
						{
							"ID":"F_Middle_B",
							"PosX":"-0.3",
							"PosY":"-0.233139",
							"RID":"83000451"
						}
					],
					"TimeSec":"16"
				}
			],
			"Title":"Untitled"
		},
		{
			"Events":
			[
				{
					"Scripts":
					[
						{
							"PosX":"0",
							"PosY":"0",
							"TargetRID":"81000226",
							"Text":"animate count-idle"
						},
						{
							"PosX":"0.158147",
							"PosY":"0.003195",
							"TargetRID":"81000227",
							"Text":"animate count-idle"
						},
						{
							"PosX":"0.15655",
							"PosY":"-0.007987",
							"TargetRID":"81000229",
							"Text":"animate count-idle"
						},
						{
							"PosX":"0.092593",
							"PosY":"0.109259",
							"TargetRID":"81000234",
							"Text":"animate count-idle"
						}
					],
					"TimeSec":"0"
				},
				{
					"Monsters":
					[
						{
							"ID":"F_Middle_B",
							"PosX":"-0.3",
							"PosY":"0.233139",
							"RID":"83000507"
						},
						{
							"ID":"F_Normal",
							"PosX":"-0.44",
							"PosY":"0.449625",
							"RID":"83000517"
						}
					],
					"TimeSec":"6"
				},
				{
					"Monsters":
					[
						{
							"ID":"F_Middle_B",
							"PosX":"-0.3",
							"PosY":"0.233139",
							"RID":"83000508"
						},
						{
							"ID":"F_Normal_B",
							"PosX":"-0.44",
							"PosY":"0.449625",
							"RID":"83000518"
						}
					],
					"TimeSec":"8"
				},
				{
					"Monsters":
					[
						{
							"ID":"F_Middle_B",
							"PosX":"-0.3",
							"PosY":"0.233139",
							"RID":"83000509"
						},
						{
							"ID":"F_Normal",
							"PosX":"-0.44",
							"PosY":"0.449625",
							"RID":"83000519"
						}
					],
					"TimeSec":"10"
				},
				{
					"Monsters":
					[
						{
							"ID":"F_Middle_B",
							"PosX":"-0.3",
							"PosY":"0.233139",
							"RID":"83000510"
						},
						{
							"ID":"F_Normal_B",
							"PosX":"-0.44",
							"PosY":"0.449625",
							"RID":"83000520"
						}
					],
					"TimeSec":"12"
				},
				{
					"Monsters":
					[
						{
							"ID":"F_Middle_B",
							"PosX":"-0.3",
							"PosY":"0.233139",
							"RID":"83000511"
						},
						{
							"ID":"F_Normal",
							"PosX":"-0.44",
							"PosY":"0.449625",
							"RID":"83000521"
						}
					],
					"TimeSec":"14"
				},
				{
					"Monsters":
					[
						{
							"ID":"F_Middle_B",
							"PosX":"-0.3",
							"PosY":"0.233139",
							"RID":"83000512"
						},
						{
							"ID":"F_Normal_B",
							"PosX":"-0.44",
							"PosY":"0.449625",
							"RID":"83000522"
						}
					],
					"TimeSec":"16"
				}
			],
			"Title":"Untitled"
		},
		{
			"Events":
			[
				{
					"Scripts":
					[
						{
							"PosX":"0",
							"PosY":"0",
							"TargetRID":"81000230",
							"Text":"animate count-idle"
						},
						{
							"PosX":"-0.222222",
							"PosY":"-0.033333",
							"TargetRID":"81000231",
							"Text":"animate count-idle"
						},
						{
							"PosX":"0",
							"PosY":"0",
							"TargetRID":"81000249",
							"Text":"animate count-idle"
						},
						{
							"PosX":"0",
							"PosY":"0",
							"TargetRID":"81000250",
							"Text":"animate count-idle"
						}
					],
					"TimeSec":"0"
				},
				{
					"Monsters":
					[
						{
							"ID":"F_Middle_B",
							"PosX":"-0.3",
							"PosY":"-0.233139",
							"RID":"83000480"
						},
						{
							"ID":"F_Middle_B",
							"PosX":"-0.44",
							"PosY":"-0.449625",
							"RID":"83000492"
						}
					],
					"TimeSec":"6"
				},
				{
					"Monsters":
					[
						{
							"ID":"F_Middle",
							"PosX":"-0.3",
							"PosY":"-0.233139",
							"RID":"83000481"
						},
						{
							"ID":"F_Middle_B",
							"PosX":"-0.44",
							"PosY":"-0.449625",
							"RID":"83000493"
						}
					],
					"TimeSec":"8"
				},
				{
					"Monsters":
					[
						{
							"ID":"F_Middle_B",
							"PosX":"-0.3",
							"PosY":"-0.233139",
							"RID":"83000482"
						},
						{
							"ID":"F_Middle_B",
							"PosX":"-0.44",
							"PosY":"-0.449625",
							"RID":"83000494"
						}
					],
					"TimeSec":"10"
				},
				{
					"Monsters":
					[
						{
							"ID":"F_Middle",
							"PosX":"-0.3",
							"PosY":"-0.233139",
							"RID":"83000483"
						},
						{
							"ID":"F_Middle_B",
							"PosX":"-0.44",
							"PosY":"-0.449625",
							"RID":"83000495"
						}
					],
					"TimeSec":"12"
				},
				{
					"Monsters":
					[
						{
							"ID":"F_Middle_B",
							"PosX":"-0.3",
							"PosY":"-0.233139",
							"RID":"83000484"
						},
						{
							"ID":"F_Middle_B",
							"PosX":"-0.44",
							"PosY":"-0.449625",
							"RID":"83000496"
						}
					],
					"TimeSec":"14"
				}
			],
			"Title":"Untitled"
		},
		{
			"Events":
			[
				{
					"Scripts":
					[
						{
							"PosX":"0",
							"PosY":"0",
							"TargetRID":"81000226",
							"Text":"animate count-idle"
						},
						{
							"PosX":"0.228435",
							"PosY":"0.023962",
							"TargetRID":"81000229",
							"Text":"animate count-idle"
						},
						{
							"PosX":"0.207668",
							"PosY":"0.001597",
							"TargetRID":"81000230",
							"Text":"animate count-idle"
						},
						{
							"PosX":"-0.161111",
							"PosY":"-0.07037",
							"TargetRID":"81000234",
							"Text":"animate count-idle"
						},
						{
							"PosX":"0",
							"PosY":"0",
							"TargetRID":"81000250",
							"Text":"animate count-idle"
						}
					],
					"TimeSec":"0"
				},
				{
					"Monsters":
					[
						{
							"ID":"F_MiddleBoss",
							"PosX":"-0.44",
							"PosY":"0.449625",
							"RID":"83000583"
						},
						{
							"ID":"F_MiddleBoss",
							"PosX":"-0.44",
							"PosY":"-0.449625",
							"RID":"83000584"
						}
					],
					"TimeSec":"6"
				},
				{
					"Monsters":
					[
						{
							"ID":"F_Middle",
							"PosX":"-0.44",
							"PosY":"0.449625",
							"RID":"83000530"
						},
						{
							"ID":"F_Middle",
							"PosX":"-0.44",
							"PosY":"-0.449625",
							"RID":"83000535"
						}
					],
					"TimeSec":"8"
				},
				{
					"Monsters":
					[
						{
							"ID":"F_Fast",
							"PosX":"-0.44",
							"PosY":"0.449625",
							"RID":"83000531"
						},
						{
							"ID":"F_Fast",
							"PosX":"-0.44",
							"PosY":"-0.449625",
							"RID":"83000536"
						}
					],
					"TimeSec":"10"
				},
				{
					"Monsters":
					[
						{
							"ID":"F_Middle",
							"PosX":"-0.44",
							"PosY":"0.449625",
							"RID":"83000532"
						},
						{
							"ID":"F_Middle",
							"PosX":"-0.44",
							"PosY":"-0.449625",
							"RID":"83000537"
						}
					],
					"TimeSec":"12"
				},
				{
					"Monsters":
					[
						{
							"ID":"F_Middle",
							"PosX":"-0.44",
							"PosY":"-0.449251",
							"RID":"83000603"
						},
						{
							"ID":"F_Middle",
							"PosX":"-0.44",
							"PosY":"0.449251",
							"RID":"83000604"
						}
					],
					"TimeSec":"14"
				}
			],
			"Title":"Untitled"
		},
		{
			"Events":
			[
				{
					"Scripts":
					[
						{
							"PosX":"0.15655",
							"PosY":"0.051118",
							"TargetRID":"81000227",
							"Text":"animate count-idle"
						},
						{
							"PosX":"-0.2",
							"PosY":"-0.046296",
							"TargetRID":"81000234",
							"Text":"animate count-idle"
						},
						{
							"PosX":"0.080935",
							"PosY":"-0.064748",
							"TargetRID":"81000249",
							"Text":"animate count-idle"
						}
					],
					"TimeSec":"0"
				},
				{
					"Monsters":
					[
						{
							"ID":"F_Middle_B",
							"PosX":"-0.3",
							"PosY":"-0.233139",
							"RID":"83000549"
						},
						{
							"ID":"F_Middle_B",
							"PosX":"-0.3",
							"PosY":"0.233139",
							"RID":"83000553"
						}
					],
					"TimeSec":"6"
				},
				{
					"Monsters":
					[
						{
							"ID":"F_MiddleBoss",
							"PosX":"-0.3",
							"PosY":"-0.233139",
							"RID":"83000550"
						},
						{
							"ID":"F_MiddleBoss",
							"PosX":"-0.3",
							"PosY":"0.233139",
							"RID":"83000554"
						}
					],
					"TimeSec":"8"
				},
				{
					"Monsters":
					[
						{
							"ID":"F_Middle_B",
							"PosX":"-0.3",
							"PosY":"-0.233139",
							"RID":"83000551"
						},
						{
							"ID":"F_Middle_B",
							"PosX":"-0.3",
							"PosY":"0.233139",
							"RID":"83000555"
						}
					],
					"TimeSec":"10"
				},
				{
					"Monsters":
					[
						{
							"ID":"F_MiddleBoss",
							"PosX":"-0.3",
							"PosY":"-0.233139",
							"RID":"83000552"
						},
						{
							"ID":"F_MiddleBoss",
							"PosX":"-0.3",
							"PosY":"0.233139",
							"RID":"83000556"
						}
					],
					"TimeSec":"12"
				}
			],
			"Title":"Untitled"
		},
		{
			"Events":
			[
				{
					"Scripts":
					[
						{
							"PosX":"0.142086",
							"PosY":"0.021583",
							"TargetRID":"81000226",
							"Text":"animate count-idle"
						},
						{
							"PosX":"0.172524",
							"PosY":"0.043131",
							"TargetRID":"81000229",
							"Text":"animate count-idle"
						},
						{
							"PosX":"0.172524",
							"PosY":"-0.041534",
							"TargetRID":"81000230",
							"Text":"animate count-idle"
						},
						{
							"PosX":"-0.257407",
							"PosY":"-0.074074",
							"TargetRID":"81000234",
							"Text":"animate count-idle"
						},
						{
							"PosX":"0",
							"PosY":"0",
							"TargetRID":"81000250",
							"Text":"animate count-idle"
						}
					],
					"TimeSec":"0"
				},
				{
					"Monsters":
					[
						{
							"ID":"F_Middle_B",
							"PosX":"-0.44",
							"PosY":"0.449625",
							"RID":"83000585"
						},
						{
							"ID":"F_Middle_B",
							"PosX":"-0.44",
							"PosY":"-0.449625",
							"RID":"83000589"
						}
					],
					"TimeSec":"6"
				},
				{
					"Monsters":
					[
						{
							"ID":"F_MiddleBoss",
							"PosX":"-0.44",
							"PosY":"0.449625",
							"RID":"83000586"
						},
						{
							"ID":"F_MiddleBoss",
							"PosX":"-0.44",
							"PosY":"-0.449625",
							"RID":"83000590"
						}
					],
					"TimeSec":"8"
				},
				{
					"Monsters":
					[
						{
							"ID":"F_Middle_B",
							"PosX":"-0.44",
							"PosY":"0.449625",
							"RID":"83000587"
						},
						{
							"ID":"F_Middle_B",
							"PosX":"-0.44",
							"PosY":"-0.449625",
							"RID":"83000591"
						}
					],
					"TimeSec":"10"
				},
				{
					"Monsters":
					[
						{
							"ID":"F_Fast",
							"PosX":"-0.44",
							"PosY":"0.45",
							"RID":"83000601"
						},
						{
							"ID":"F_Fast",
							"PosX":"-0.44",
							"PosY":"-0.45",
							"RID":"83000602"
						}
					],
					"TimeSec":"12"
				}
			],
			"Title":"Untitled"
		}
	]
}
