{
	"BuildNumber":"1",
	"MapName":"map_49",
	"MissionLastRID":"83999999",
	"MonsterLastRID":"83000064",
	"ToolType":"stagetool_f1",
	"ToolVersion":"2",
	"Waves":
	[
		{
			"Events":
			[
				{
					"Scripts":
					[
						{
							"PosX":"0.211765",
							"PosY":"0.02549",
							"TargetRID":"81000275",
							"Text":"animate count-idle"
						}
					],
					"TimeSec":"0"
				},
				{
					"Monsters":
					[
						{
							"ID":"I_Slime",
							"PosX":"-0.36",
							"PosY":"0.333056",
							"RID":"83000000"
						}
					],
					"TimeSec":"6"
				},
				{
					"Monsters":
					[
						{
							"ID":"I_Slime",
							"PosX":"-0.36",
							"PosY":"0.333056",
							"RID":"83000001"
						}
					],
					"TimeSec":"8"
				},
				{
					"Monsters":
					[
						{
							"ID":"I_Slime",
							"PosX":"-0.36",
							"PosY":"0.333056",
							"RID":"83000002"
						}
					],
					"TimeSec":"10"
				},
				{
					"Monsters":
					[
						{
							"ID":"I_Slime",
							"PosX":"-0.36",
							"PosY":"0.333056",
							"RID":"83000003"
						}
					],
					"TimeSec":"12"
				},
				{
					"Monsters":
					[
						{
							"ID":"I_Slime",
							"PosX":"-0.36",
							"PosY":"0.333056",
							"RID":"83000004"
						}
					],
					"TimeSec":"14"
				}
			],
			"Title":"Untitled"
		},
		{
			"Events":
			[
				{
					"Scripts":
					[
						{
							"PosX":"-0.027451",
							"PosY":"-0.090196",
							"TargetRID":"81000303",
							"Text":"animate count-idle"
						}
					],
					"TimeSec":"0"
				},
				{
					"Monsters":
					[
						{
							"ID":"I_Slime",
							"PosX":"0.3",
							"PosY":"0.41632",
							"RID":"83000015"
						}
					],
					"TimeSec":"6"
				},
				{
					"Monsters":
					[
						{
							"ID":"I_Slime",
							"PosX":"0.3",
							"PosY":"0.41632",
							"RID":"83000016"
						}
					],
					"TimeSec":"8"
				},
				{
					"Monsters":
					[
						{
							"ID":"I_Slime",
							"PosX":"0.3",
							"PosY":"0.41632",
							"RID":"83000017"
						}
					],
					"TimeSec":"10"
				},
				{
					"Monsters":
					[
						{
							"ID":"I_Slime",
							"PosX":"0.3",
							"PosY":"0.41632",
							"RID":"83000018"
						}
					],
					"TimeSec":"12"
				},
				{
					"Monsters":
					[
						{
							"ID":"I_Slime",
							"PosX":"0.3",
							"PosY":"0.41632",
							"RID":"83000019"
						}
					],
					"TimeSec":"14"
				}
			],
			"Title":"Untitled"
		},
		{
			"Events":
			[
				{
					"Scripts":
					[
						{
							"PosX":"-0.033333",
							"PosY":"0.160784",
							"TargetRID":"81000274",
							"Text":"animate count-idle"
						},
						{
							"PosX":"0.060784",
							"PosY":"0.023529",
							"TargetRID":"81000275",
							"Text":"animate count-idle"
						}
					],
					"TimeSec":"0"
				},
				{
					"Monsters":
					[
						{
							"ID":"I_Slime",
							"PosX":"0.36",
							"PosY":"-0.41632",
							"RID":"83000020"
						},
						{
							"ID":"I_Slime",
							"PosX":"-0.36",
							"PosY":"0.333056",
							"RID":"83000025"
						}
					],
					"TimeSec":"6"
				},
				{
					"Monsters":
					[
						{
							"ID":"I_Slime",
							"PosX":"0.36",
							"PosY":"-0.41632",
							"RID":"83000021"
						},
						{
							"ID":"I_Slime",
							"PosX":"-0.36",
							"PosY":"0.333056",
							"RID":"83000026"
						}
					],
					"TimeSec":"8"
				},
				{
					"Monsters":
					[
						{
							"ID":"I_Slime",
							"PosX":"0.36",
							"PosY":"-0.41632",
							"RID":"83000022"
						},
						{
							"ID":"I_Slime",
							"PosX":"-0.36",
							"PosY":"0.333056",
							"RID":"83000027"
						}
					],
					"TimeSec":"10"
				},
				{
					"Monsters":
					[
						{
							"ID":"I_Slime",
							"PosX":"0.36",
							"PosY":"-0.41632",
							"RID":"83000023"
						},
						{
							"ID":"I_Slime",
							"PosX":"-0.36",
							"PosY":"0.333056",
							"RID":"83000028"
						}
					],
					"TimeSec":"12"
				},
				{
					"Monsters":
					[
						{
							"ID":"I_Slime",
							"PosX":"0.36",
							"PosY":"-0.41632",
							"RID":"83000024"
						},
						{
							"ID":"I_Slime",
							"PosX":"-0.36",
							"PosY":"0.333056",
							"RID":"83000029"
						}
					],
					"TimeSec":"14"
				}
			],
			"Title":"Untitled"
		},
		{
			"Events":
			[
				{
					"Scripts":
					[
						{
							"PosX":"-0.039216",
							"PosY":"-0.147059",
							"TargetRID":"81000303",
							"Text":"animate count-idle"
						}
					],
					"TimeSec":"0"
				},
				{
					"Monsters":
					[
						{
							"ID":"I_Slime",
							"PosX":"0.3",
							"PosY":"0.41632",
							"RID":"83000040"
						}
					],
					"TimeSec":"6"
				},
				{
					"Monsters":
					[
						{
							"ID":"I_Slime",
							"PosX":"0.3",
							"PosY":"0.41632",
							"RID":"83000041"
						}
					],
					"TimeSec":"8"
				},
				{
					"Monsters":
					[
						{
							"ID":"I_Slime",
							"PosX":"0.3",
							"PosY":"0.41632",
							"RID":"83000042"
						}
					],
					"TimeSec":"11"
				},
				{
					"Monsters":
					[
						{
							"ID":"I_Slime",
							"PosX":"0.3",
							"PosY":"0.41632",
							"RID":"83000043"
						}
					],
					"TimeSec":"13"
				},
				{
					"Monsters":
					[
						{
							"ID":"I_Slime",
							"PosX":"0.3",
							"PosY":"0.41632",
							"RID":"83000045"
						}
					],
					"TimeSec":"16"
				},
				{
					"Monsters":
					[
						{
							"ID":"I_Slime",
							"PosX":"0.3",
							"PosY":"0.41632",
							"RID":"83000046"
						}
					],
					"TimeSec":"18"
				}
			],
			"Title":"Untitled"
		},
		{
			"Events":
			[
				{
					"Scripts":
					[
						{
							"PosX":"-0.043137",
							"PosY":"0.182353",
							"TargetRID":"81000274",
							"Text":"animate count-idle"
						},
						{
							"PosX":"0.182353",
							"PosY":"0.041176",
							"TargetRID":"81000275",
							"Text":"animate count-idle"
						},
						{
							"PosX":"-0.101961",
							"PosY":"-0.096078",
							"TargetRID":"81000303",
							"Text":"animate count-idle"
						}
					],
					"TimeSec":"0"
				},
				{
					"Monsters":
					[
						{
							"ID":"I_Slime_B",
							"PosX":"-0.36",
							"PosY":"0.333056",
							"RID":"83000062"
						},
						{
							"ID":"I_Slime_B",
							"PosX":"0.3",
							"PosY":"0.41632",
							"RID":"83000063"
						},
						{
							"ID":"I_Slime_B",
							"PosX":"0.36",
							"PosY":"-0.41632",
							"RID":"83000064"
						}
					],
					"TimeSec":"6"
				},
				{
					"Monsters":
					[
						{
							"ID":"I_Slime",
							"PosX":"0.36",
							"PosY":"-0.41632",
							"RID":"83000048"
						},
						{
							"ID":"I_Slime",
							"PosX":"-0.36",
							"PosY":"0.333056",
							"RID":"83000053"
						},
						{
							"ID":"I_Slime",
							"PosX":"0.3",
							"PosY":"0.41632",
							"RID":"83000058"
						}
					],
					"TimeSec":"8"
				},
				{
					"Monsters":
					[
						{
							"ID":"I_Slime",
							"PosX":"0.36",
							"PosY":"-0.41632",
							"RID":"83000049"
						},
						{
							"ID":"I_Slime",
							"PosX":"-0.36",
							"PosY":"0.333056",
							"RID":"83000054"
						},
						{
							"ID":"I_Slime",
							"PosX":"0.3",
							"PosY":"0.41632",
							"RID":"83000059"
						}
					],
					"TimeSec":"10"
				},
				{
					"Monsters":
					[
						{
							"ID":"I_Slime",
							"PosX":"0.36",
							"PosY":"-0.41632",
							"RID":"83000050"
						},
						{
							"ID":"I_Slime",
							"PosX":"-0.36",
							"PosY":"0.333056",
							"RID":"83000055"
						},
						{
							"ID":"I_Slime",
							"PosX":"0.3",
							"PosY":"0.41632",
							"RID":"83000060"
						}
					],
					"TimeSec":"12"
				},
				{
					"Monsters":
					[
						{
							"ID":"I_Slime",
							"PosX":"0.36",
							"PosY":"-0.41632",
							"RID":"83000051"
						},
						{
							"ID":"I_Slime",
							"PosX":"-0.36",
							"PosY":"0.333056",
							"RID":"83000056"
						},
						{
							"ID":"I_Slime",
							"PosX":"0.3",
							"PosY":"0.41632",
							"RID":"83000061"
						}
					],
					"TimeSec":"14"
				}
			],
			"Title":"Untitled"
		}
	]
}
